{
  "creds": {
    "noiseKey": {
      "private": {
        "type": "Buffer",
        "data": "+G4uZSnjAtJxWZEdxUC9T2asWJLjbauusWvCyPE9XnQ="
      },
      "public": {
        "type": "Buffer",
        "data": "PpUQkIya/Ov4xbSnHdSKYYJrkGi5fG61euUWhNEkqnA="
      }
    },
    "signedIdentityKey": {
      "private": {
        "type": "Buffer",
        "data": "IF2vYbkxlMuJh9IpP8ejqVUvn8TLiRUGraLyeB7ciWc="
      },
      "public": {
        "type": "Buffer",
        "data": "YahpmWYWDvledcKjoiCXJRXqzW/OHagWr97tTX6veXY="
      }
    },
    "signedPreKey": {
      "keyPair": {
        "private": {
          "type": "Buffer",
          "data": "2GrcCUOiq2pqRSdl8di/AAgW+6C3ZS0ULJXNx6TVN1k="
        },
        "public": {
          "type": "Buffer",
          "data": "dLewgWUox4QGO8sKzQ2pgm7nvPCdKSmMQfvYvkg/aw0="
        }
      },
      "signature": {
        "type": "Buffer",
        "data": "WyJLZhTC6bxAmSj9cHRtYIumSMlqSkQex1xEVH/WoNwd/raAu2x+pVSxx6tEuep7wlRznREyR7OHKsyb9m9fBw=="
      },
      "keyId": 1
    },
    "registrationId": 49,
    "advSecretKey": "or0Ut791h3UE8EA1XR269sp1KT7+53PnXIOpsoGLnmU=",
    "processedHistoryMessages": [
      {
        "key": {
          "remoteJid": "62895605816958@s.whatsapp.net",
          "fromMe": true,
          "id": "CD18B45A2E9E57EF6509030018A9B8BD"
        },
        "timestamp": 1658320007
      },
      {
        "key": {
          "remoteJid": "62895605816958@s.whatsapp.net",
          "fromMe": true,
          "id": "DAC09EBE97F85DA51FE95978BB10879C"
        },
        "timestamp": 1658320008
      },
      {
        "key": {
          "remoteJid": "62895605816958@s.whatsapp.net",
          "fromMe": true,
          "id": "DC933E7D565BE053E768AA9BED39F98C"
        },
        "timestamp": 1658320035
      }
    ],
    "nextPreKeyId": 33,
    "firstUnuploadedPreKeyId": 33,
    "accountSettings": {
      "unarchiveChats": false
    },
    "account": {
      "details": "CJ7RmuwGEIDp35YGGAU=",
      "accountSignature": "9UeKqN+H89aVHKMq+LGyT5DLgDRPhi5FxLpgeICbGrBEoMbiA4q56aRLMbyZCXY5dbYJRVAxqrnoaOgjpJynAw==",
      "deviceSignature": "tobLiqLy6GhOmeydj/ydWHV0D8MLkveuliZ44mYRJstqduqssk1cWIHQCc+N72jB4JmSScjUhkCz8dyfipyzBA=="
    },
    "me": {
      "id": "62895605816958:29@s.whatsapp.net",
      "name": "ZeroBot-MD"
    },
    "signalIdentities": [
      {
        "identifier": {
          "name": "62895605816958:29@s.whatsapp.net",
          "deviceId": 0
        },
        "identifierKey": {
          "type": "Buffer",
          "data": "BcyiFGTEVlvRIflw5wu1WmD0QuWM+Y25swYxLro87mYD"
        }
      }
    ],
    "platform": "smba",
    "lastAccountSyncTimestamp": 1658320127,
    "myAppStateKeyId": "AAAAAEbm"
  },
  "keys": {
    "preKeys": {
      "1": {
        "private": {
          "type": "Buffer",
          "data": "WJiNHiCZRDpNRiFkw5dINyT9qinwShxEYzXsnSveIn8="
        },
        "public": {
          "type": "Buffer",
          "data": "JRQrR73+iynDCQ9otUPO68TG9QRwUsOh5ljk/AuEcHw="
        }
      },
      "2": {
        "private": {
          "type": "Buffer",
          "data": "UORWRTkDV5b6RxnVWYTuoJRpCYW1qRIAruUBinTR8Uk="
        },
        "public": {
          "type": "Buffer",
          "data": "ypwcZfxWMMRI53N2PzF/oA+vkiBD66LMk/XwqB7zODA="
        }
      },
      "3": {
        "private": {
          "type": "Buffer",
          "data": "QEKJnOg5HOQ+7YIh81Wig918vN8TWCOm49bnUTpDFWg="
        },
        "public": {
          "type": "Buffer",
          "data": "TCgjKQqMyGaRixZ+oi0QnNNS7Tvc09eBZEvIXezA+VQ="
        }
      },
      "4": null,
      "5": null,
      "6": null,
      "7": {
        "private": {
          "type": "Buffer",
          "data": "CIR/EIlDY8oD67lS3xev20odxTarxm56ZXoW6XYEj24="
        },
        "public": {
          "type": "Buffer",
          "data": "6NSEQPEfRkPJ4aeLuPgx6wY2EHpsDgpqrspdlrAnDEI="
        }
      },
      "8": {
        "private": {
          "type": "Buffer",
          "data": "yLZRswYv557UduR2L53WirzF35qdhQGrYN8qdPgru24="
        },
        "public": {
          "type": "Buffer",
          "data": "PF/hl5i0FnzcUPfYGbRa+k0enn2bS4+z/8uIYevkx0Y="
        }
      },
      "9": {
        "private": {
          "type": "Buffer",
          "data": "YIZrjCx5q3I/VjyHvxdbytI+/onOatZ7DwTSwk8IG3g="
        },
        "public": {
          "type": "Buffer",
          "data": "gA86SlWO5S4JpIfohh4B821KRJh677xdIn2Ut5OHZl8="
        }
      },
      "10": {
        "private": {
          "type": "Buffer",
          "data": "gHGkQOInwuMstWV6o1WFX3PQgeA9w4NIS/24IFI9ym0="
        },
        "public": {
          "type": "Buffer",
          "data": "q1heMtAbRkP6xnYRusFGvfPV/4zpEaokyiE1NoxFGlc="
        }
      },
      "11": {
        "private": {
          "type": "Buffer",
          "data": "mGjfXsT2a4im4sw9XTZTAcXwyNI2c748txcNfC+RlnU="
        },
        "public": {
          "type": "Buffer",
          "data": "2UKkbmQBBahdOvaHzTlPHfxZfrkU5l7J8dEDBX4p+EA="
        }
      },
      "12": {
        "private": {
          "type": "Buffer",
          "data": "6AaVUQv7rXtEOe/Kcfw67+745v6tlk56TzeMBTLZC3I="
        },
        "public": {
          "type": "Buffer",
          "data": "dbVgR1/+HWsFaalrjdVwbR0/QOBtXEzRrsHXRSeEmQs="
        }
      },
      "13": {
        "private": {
          "type": "Buffer",
          "data": "6GkpogxqTULk0loDnu17zu7acDa2+KLP7iDEo7saamI="
        },
        "public": {
          "type": "Buffer",
          "data": "perVD4I3fsV2GtGDawPLkgIWktkhYvxlAdkQKdNF4k8="
        }
      },
      "14": {
        "private": {
          "type": "Buffer",
          "data": "UP7qL8iu2lg5EkNWVgqPWJtj7Nh+QvQnK8hZNK0Lf3c="
        },
        "public": {
          "type": "Buffer",
          "data": "PY8CIJ/PnO/0+FHvyM0qmgTcJVcuAxFF+BEZYmzpFx8="
        }
      },
      "15": {
        "private": {
          "type": "Buffer",
          "data": "sAYpaQa1QgPmT5pS1NJCAPMXrzAmausQXqfW4VJkvFA="
        },
        "public": {
          "type": "Buffer",
          "data": "sP7mZWMQASgwMV2+qPbN7BgfZDBvUzzhwBIyCWMGFAI="
        }
      },
      "16": {
        "private": {
          "type": "Buffer",
          "data": "+ILpjmd1P51pmGg0MsVS8kvso1aDoGzeczVjGbj5dVA="
        },
        "public": {
          "type": "Buffer",
          "data": "O+u2sSsVGfoMxvB7sOqN3qYxmSh3+ndnHVAZ6SMN5BM="
        }
      },
      "17": {
        "private": {
          "type": "Buffer",
          "data": "qP/ENwQxczSYn1CWRzrEZc9+78v4DiVi+ipO3jIkfWI="
        },
        "public": {
          "type": "Buffer",
          "data": "BMsEjafXNBNN2UwMDwhYaV7co5fcVl8cKLfW6swGa24="
        }
      },
      "18": null,
      "19": {
        "private": {
          "type": "Buffer",
          "data": "mJUd1ppL6MOB0QCO0MjBot63Isqgh+3aM6uAbiLXYW8="
        },
        "public": {
          "type": "Buffer",
          "data": "nDxtd/AHiJW/Sjia25Oks0Qw7YjKHNH8dK+wWc1G+SA="
        }
      },
      "20": {
        "private": {
          "type": "Buffer",
          "data": "OBnKYz4AvTl1MPw9hTPhYPmDil/SBz0jEne7ooQG3k8="
        },
        "public": {
          "type": "Buffer",
          "data": "fmZfQRBwQu9UjWUFTxU7rdDURk4PD5vrpg4ia+ExdDQ="
        }
      },
      "21": null,
      "22": null,
      "23": null,
      "24": {
        "private": {
          "type": "Buffer",
          "data": "kBiQZvbwHnO4gky9C9GuN0FTF5StpH9LsFy7sn3WamQ="
        },
        "public": {
          "type": "Buffer",
          "data": "6w440av7RPPB6n9hogs4Tl4RsTqJUa9vfKM2XiX5y14="
        }
      },
      "25": null,
      "26": null,
      "27": null,
      "28": {
        "private": {
          "type": "Buffer",
          "data": "yHm/w+dJgE+OAwVQcJQ/OyKzN+Glo7+xEEtPJPW6LVw="
        },
        "public": {
          "type": "Buffer",
          "data": "BZS6tdBrORgxpI38j/Vn8rAYfIC3jrHDpHGspElmpn4="
        }
      },
      "29": null,
      "30": null,
      "31": {
        "private": {
          "type": "Buffer",
          "data": "YPh7Pm107FfI2CA6TeySQf/N1DijX/3g/OsL1r5Wu1c="
        },
        "public": {
          "type": "Buffer",
          "data": "BkHXkXL3u91nbWz7kguCKDJgkltt7AWQzKnCCuh4djw="
        }
      },
      "32": {
        "private": {
          "type": "Buffer",
          "data": "AOYmVzsr6NJVaB1UoyXzLxbU9pXcMRhXB8wu06bSJ2M="
        },
        "public": {
          "type": "Buffer",
          "data": "qnqmkz1DNpA9iWmk6lHHHuIH0plauP1MqNDcOuY6WRM="
        }
      }
    },
    "sessions": {
      "62895605816958.0": {
        "_sessions": {
          "Bdbg+V+4G3V52h8NRADo07ZBKlk1V16zq+Uw4bkAINcu": {
            "registrationId": 1604883608,
            "currentRatchet": {
              "ephemeralKeyPair": {
                "pubKey": "BQacbY8ujzpp9g1drXHvr3djXLHZfhLnhNTxp3jv7t1A",
                "privKey": "eObp7FxL7Yc0nkNZfkxYMpygY/L+h1SBV6BLXzEWpm0="
              },
              "lastRemoteEphemeralKey": "Bb523ss25fE9p+XcmAe6HTEjNv6jJ8AarcXbMj3+aLIK",
              "previousCounter": 1,
              "rootKey": "HGNgsSnzxlcklEdrQvsXBObXWRCcvH2qcdJn5mY0EQ8="
            },
            "indexInfo": {
              "baseKey": "Bdbg+V+4G3V52h8NRADo07ZBKlk1V16zq+Uw4bkAINcu",
              "baseKeyType": 2,
              "closed": 1658387708367,
              "used": 1658320034924,
              "created": 1658320005454,
              "remoteIdentityKey": "BcyiFGTEVlvRIflw5wu1WmD0QuWM+Y25swYxLro87mYD"
            },
            "_chains": {
              "BWQlaxvdi1xHvz+99PExVPjAJQiOlD3x6z9LxexqKIZj": {
                "chainKey": {
                  "counter": 4
                },
                "chainType": 2,
                "messageKeys": {}
              },
              "Bb523ss25fE9p+XcmAe6HTEjNv6jJ8AarcXbMj3+aLIK": {
                "chainKey": {
                  "counter": 1,
                  "key": "mSLDol8f5kLu//3tEf2013WHD+/o4KPcHm/iIPabmrY="
                },
                "chainType": 2,
                "messageKeys": {}
              },
              "BQacbY8ujzpp9g1drXHvr3djXLHZfhLnhNTxp3jv7t1A": {
                "chainKey": {
                  "counter": 22,
                  "key": "Ur1wbhUN0G6Vdadv0TilFQRCnSJThatFTIGqA4tVSlA="
                },
                "chainType": 1,
                "messageKeys": {}
              }
            }
          },
          "BeowFpPVvnn2wabf6EqZKm/N68ovYUP5RR2z+G4s2dYU": {
            "registrationId": 1604883608,
            "currentRatchet": {
              "ephemeralKeyPair": {
                "pubKey": "BUFiqLY01gR+3A//AMtiTThrHLgp8cSSLy7bpSDLGk5q",
                "privKey": "UJZoDDkgJ8+UPQVVnQoSo7OXj6lGdw9Oi6WIUqY1YFo="
              },
              "lastRemoteEphemeralKey": "BSO9D84Fa9iNhmEK2+6dr1eNSL2smy+ZmkifFclCOgVK",
              "previousCounter": 0,
              "rootKey": "RNoix5vUgFi3waPnihfjkZJcmr606bSKh2aogHSm5xw="
            },
            "indexInfo": {
              "baseKey": "BeowFpPVvnn2wabf6EqZKm/N68ovYUP5RR2z+G4s2dYU",
              "baseKeyType": 1,
              "closed": 1658387713178,
              "used": 1658387708346,
              "created": 1658387708346,
              "remoteIdentityKey": "BcyiFGTEVlvRIflw5wu1WmD0QuWM+Y25swYxLro87mYD"
            },
            "_chains": {
              "BUFiqLY01gR+3A//AMtiTThrHLgp8cSSLy7bpSDLGk5q": {
                "chainKey": {
                  "counter": -1,
                  "key": "2Rl2iD4PT9z/op3Ux/rTWCLWebj/hA8pVaTNtGcgd64="
                },
                "chainType": 1,
                "messageKeys": {}
              }
            },
            "pendingPreKey": {
              "signedKeyId": 1,
              "baseKey": "BeowFpPVvnn2wabf6EqZKm/N68ovYUP5RR2z+G4s2dYU",
              "preKeyId": 6950715
            }
          },
          "BaqfAb2gIliZ/5wSbpL+RZnrXFSftQUgpWBB4JflS3Fg": {
            "registrationId": 1604883608,
            "currentRatchet": {
              "ephemeralKeyPair": {
                "pubKey": "BR0PAICyfOCo3RrNt+CEJwIiXV+jOA4vdFjVo29AGHIZ",
                "privKey": "EITRmZthwDEDVeMm6lHwXg2xvQ0YX//G4wTNMYgVhGg="
              },
              "lastRemoteEphemeralKey": "BSO9D84Fa9iNhmEK2+6dr1eNSL2smy+ZmkifFclCOgVK",
              "previousCounter": 0,
              "rootKey": "zceLLM9mAfUlNicD96DCIF9mVQt/9mTr2Nc1Ju9ifOw="
            },
            "indexInfo": {
              "baseKey": "BaqfAb2gIliZ/5wSbpL+RZnrXFSftQUgpWBB4JflS3Fg",
              "baseKeyType": 1,
              "closed": 1658387758895,
              "used": 1658387713163,
              "created": 1658387713163,
              "remoteIdentityKey": "BcyiFGTEVlvRIflw5wu1WmD0QuWM+Y25swYxLro87mYD"
            },
            "_chains": {
              "BR0PAICyfOCo3RrNt+CEJwIiXV+jOA4vdFjVo29AGHIZ": {
                "chainKey": {
                  "counter": -1,
                  "key": "RObabt1AzrmVwicyiCEDcyIgLGBsrZF3QANNTQeRn24="
                },
                "chainType": 1,
                "messageKeys": {}
              }
            },
            "pendingPreKey": {
              "signedKeyId": 1,
              "baseKey": "BaqfAb2gIliZ/5wSbpL+RZnrXFSftQUgpWBB4JflS3Fg",
              "preKeyId": 6950684
            }
          },
          "BTPlvT1OUn663I6Nws+tv5KTSEiSszkChDoHpNb1j2pu": {
            "registrationId": 1604883608,
            "currentRatchet": {
              "ephemeralKeyPair": {
                "pubKey": "Bdr9TiSSwsXh/F82gCq7BWrSAGa1xul/kgt6iczABUgk",
                "privKey": "eIp1NXniGya8GdeoOnbjeCf2TT1ZLBWxiedQdm7gV0M="
              },
              "lastRemoteEphemeralKey": "BSO9D84Fa9iNhmEK2+6dr1eNSL2smy+ZmkifFclCOgVK",
              "previousCounter": 0,
              "rootKey": "qvzr3ACPTPNbFreugjLKDV7X5Zs0wipWjaoDwHjE2+E="
            },
            "indexInfo": {
              "baseKey": "BTPlvT1OUn663I6Nws+tv5KTSEiSszkChDoHpNb1j2pu",
              "baseKeyType": 1,
              "closed": -1,
              "used": 1658387758868,
              "created": 1658387758868,
              "remoteIdentityKey": "BcyiFGTEVlvRIflw5wu1WmD0QuWM+Y25swYxLro87mYD"
            },
            "_chains": {
              "Bdr9TiSSwsXh/F82gCq7BWrSAGa1xul/kgt6iczABUgk": {
                "chainKey": {
                  "counter": 0,
                  "key": "fTu4+nxBlCF6ufDraS6tYeksDVw+bB4sFIQXJqfOLsE="
                },
                "chainType": 1,
                "messageKeys": {}
              }
            },
            "pendingPreKey": {
              "signedKeyId": 1,
              "baseKey": "BTPlvT1OUn663I6Nws+tv5KTSEiSszkChDoHpNb1j2pu",
              "preKeyId": 6950726
            }
          }
        },
        "version": "v1"
      },
      "6289682097468.0": {
        "_sessions": {
          "BeUMNoybjOtXvrLJpxaDcU7j2kFXwOpcKzU8EcyODmAU": {
            "registrationId": 218564944,
            "currentRatchet": {
              "ephemeralKeyPair": {
                "pubKey": "BdejocEwN2CgUFKSBCPSYJBs6ifWOdrMUv81IrpQ4bxA",
                "privKey": "6Nae7W0z/1Qi6MUZecQx9EDhN+/M+6vGwYIClwiRr2Q="
              },
              "lastRemoteEphemeralKey": "BZzaAK5lKp4fILnnh5y4gzc5NyacN/phczgf8wjvomRL",
              "previousCounter": 0,
              "rootKey": "HfTitEXbLhToTVXYjyo0cHvhfgJqQltCkoLLmG/NquM="
            },
            "indexInfo": {
              "baseKey": "BeUMNoybjOtXvrLJpxaDcU7j2kFXwOpcKzU8EcyODmAU",
              "baseKeyType": 2,
              "closed": -1,
              "used": 1658320050573,
              "created": 1658320016555,
              "remoteIdentityKey": "Bck3+hGL4y3WkNq1bWXibMbXztDW482SVzlexqclCssL"
            },
            "_chains": {
              "BUp8pz1OG87+v9X8a2oTdI4I7149KXnIj8rfKDy2e+oI": {
                "chainKey": {
                  "counter": 0
                },
                "chainType": 2,
                "messageKeys": {}
              },
              "BZLW3qfDof5KwT+QxJN3vPjzB6nc8NPjQsXJp0jy2yNW": {
                "chainKey": {
                  "counter": 1
                },
                "chainType": 2,
                "messageKeys": {
                  "0": "h6BKbKWbrYGEktAOuAhhASvghGYbRLtanzS7a7wOPNM="
                }
              },
              "BazJLaQepoEsZn/U1OuSZP9nHCjvtufq72n5uxgp7ow1": {
                "chainKey": {
                  "counter": 0
                },
                "chainType": 2,
                "messageKeys": {}
              },
              "BRY5OQPMz7MDTaV9TxlK+BZmuqh+8pUw8Yxhpqb7x0lw": {
                "chainKey": {
                  "counter": 0
                },
                "chainType": 2,
                "messageKeys": {}
              },
              "BZzaAK5lKp4fILnnh5y4gzc5NyacN/phczgf8wjvomRL": {
                "chainKey": {
                  "counter": 0,
                  "key": "We7GMs1PRqysZ0C0tQQizBab8LOu+JCrE6h8NG9nUYw="
                },
                "chainType": 2,
                "messageKeys": {}
              },
              "BdejocEwN2CgUFKSBCPSYJBs6ifWOdrMUv81IrpQ4bxA": {
                "chainKey": {
                  "counter": 0,
                  "key": "gA1EbxPosid/SSJTAX/ZFf5QQjvO/i5FXy9YwYZ+9mc="
                },
                "chainType": 1,
                "messageKeys": {}
              }
            }
          }
        },
        "version": "v1"
      },
      "6289682097468:14.0": {
        "_sessions": {
          "BUUT96AMw209Z0qnBpgVDa+JcOkUXr57GWCp1KmxmpRW": {
            "registrationId": 138,
            "currentRatchet": {
              "ephemeralKeyPair": {
                "pubKey": "Bb3P4hfXKregvLZwhGsL7Y48fSIxPo8b+nnR8t2COB0t",
                "privKey": "gJohjLdAKjNFlaQW5f3K1+w9u8agBLMdsZIXMpAB4kE="
              },
              "lastRemoteEphemeralKey": "BTJI+hrifuvkHuES/Y7dXfbumT7/fBNa3+sV9xrXC3Qu",
              "previousCounter": 0,
              "rootKey": "XNxREGYrNICFMoTnF/FEY2A329Zha9wD6I1ypZlgb3Y="
            },
            "indexInfo": {
              "baseKey": "BUUT96AMw209Z0qnBpgVDa+JcOkUXr57GWCp1KmxmpRW",
              "baseKeyType": 1,
              "closed": -1,
              "used": 1658320017704,
              "created": 1658320017704,
              "remoteIdentityKey": "BSbWup1zCJmKFn1VV3CcBit1cE97a+Tk+FhOgExpMSBM"
            },
            "_chains": {
              "Bb3P4hfXKregvLZwhGsL7Y48fSIxPo8b+nnR8t2COB0t": {
                "chainKey": {
                  "counter": 4,
                  "key": "G7ZM8UiU3u5bbgldDyBjNKht6vxMI2gVnHH+BE2jMT4="
                },
                "chainType": 1,
                "messageKeys": {}
              }
            },
            "pendingPreKey": {
              "signedKeyId": 1,
              "baseKey": "BUUT96AMw209Z0qnBpgVDa+JcOkUXr57GWCp1KmxmpRW",
              "preKeyId": 9
            }
          }
        },
        "version": "v1"
      },
      "62895605816958:28.0": {
        "_sessions": {
          "BfDlfG6rJ/4EMH7sUGaaQmOzIWdT9mjuZC8DKO0/Pu5/": {
            "registrationId": 68,
            "currentRatchet": {
              "ephemeralKeyPair": {
                "pubKey": "BSKaQ+1rSSYKUcdPs5jI7Mp2KaRWn4sMv7WKWyG8i34P",
                "privKey": "OCqvW03IRHqtt4qVPeZ782XsgLr6y/ONqN0L72IEd0E="
              },
              "lastRemoteEphemeralKey": "Be8MN2rLegMkYMvzhatGJanubgVPPKYQTFm7qE9wjsos",
              "previousCounter": 0,
              "rootKey": "rnmsD1+DSgHk6CBENMm0xHGVyIhiYOxW0Tn0XRo6hco="
            },
            "indexInfo": {
              "baseKey": "BfDlfG6rJ/4EMH7sUGaaQmOzIWdT9mjuZC8DKO0/Pu5/",
              "baseKeyType": 1,
              "closed": 1658387461031,
              "used": 1658320017886,
              "created": 1658320017886,
              "remoteIdentityKey": "BXpCX1ShydItbg7yCbF3q1YuJ4YOGZuXdApPvnwzjC14"
            },
            "_chains": {
              "BSKaQ+1rSSYKUcdPs5jI7Mp2KaRWn4sMv7WKWyG8i34P": {
                "chainKey": {
                  "counter": 17,
                  "key": "1oEnKszHEp7HX8ivt2qg3aSpIc/hqorlqvCeVGBd+Dc="
                },
                "chainType": 1,
                "messageKeys": {}
              }
            },
            "pendingPreKey": {
              "signedKeyId": 1,
              "baseKey": "BfDlfG6rJ/4EMH7sUGaaQmOzIWdT9mjuZC8DKO0/Pu5/",
              "preKeyId": 383
            }
          },
          "Bd9qQgtkQYG5zXB1SBoK4bSpRLyWbHYHZrCSs2Tcikth": {
            "registrationId": 68,
            "currentRatchet": {
              "ephemeralKeyPair": {
                "pubKey": "BYbO3oUwc43Gb8JyZA6/WkBiYUjRBYEMB7mCIhC0pMIK",
                "privKey": "cN+PKb1lrE9P3K872PD0ytvnis7NB5E7xOHKnOyHz0A="
              },
              "lastRemoteEphemeralKey": "Bc9Ol7lEyrzZcyio9WP5f05t/qQ5VRCJXOlczDM2MVJC",
              "previousCounter": 0,
              "rootKey": "jPvDrUqArWAvdqL6nLTOSOXafJBD9+KGSDj+2AQwFF0="
            },
            "indexInfo": {
              "baseKey": "Bd9qQgtkQYG5zXB1SBoK4bSpRLyWbHYHZrCSs2Tcikth",
              "baseKeyType": 2,
              "closed": 1658387462741,
              "used": 1658387461149,
              "created": 1658387461149,
              "remoteIdentityKey": "BXpCX1ShydItbg7yCbF3q1YuJ4YOGZuXdApPvnwzjC14"
            },
            "_chains": {
              "Bc9Ol7lEyrzZcyio9WP5f05t/qQ5VRCJXOlczDM2MVJC": {
                "chainKey": {
                  "counter": 7,
                  "key": "AIrnF9cQtH2A7EOBRu0ZIfR7+b7FNbUREXtL+oJazJc="
                },
                "chainType": 2,
                "messageKeys": {}
              },
              "BYbO3oUwc43Gb8JyZA6/WkBiYUjRBYEMB7mCIhC0pMIK": {
                "chainKey": {
                  "counter": -1,
                  "key": "QTz7Hq/F8vxOdgSFFDYIu7hXdUnFR0jxRa/Q1w45RSo="
                },
                "chainType": 1,
                "messageKeys": {}
              }
            }
          },
          "BUlms/vaznAzm10/n491ycIAERQd/8ihjwiUFZjle21o": {
            "registrationId": 68,
            "currentRatchet": {
              "ephemeralKeyPair": {
                "pubKey": "BSHSo50V78cnKYHOWiPl4jIgF7Nk+Q7PAJDGa5pp8e97",
                "privKey": "kCqPeJ+lKFEFxlgncFafsKY0935Fx5Q25VlZfkb8G28="
              },
              "lastRemoteEphemeralKey": "Be8MN2rLegMkYMvzhatGJanubgVPPKYQTFm7qE9wjsos",
              "previousCounter": 0,
              "rootKey": "aAahVQ8THNCQb+XvTDenV3uxSZkimx58eopLBz674tI="
            },
            "indexInfo": {
              "baseKey": "BUlms/vaznAzm10/n491ycIAERQd/8ihjwiUFZjle21o",
              "baseKeyType": 1,
              "closed": 1658387462948,
              "used": 1658387462704,
              "created": 1658387462704,
              "remoteIdentityKey": "BXpCX1ShydItbg7yCbF3q1YuJ4YOGZuXdApPvnwzjC14"
            },
            "_chains": {
              "BSHSo50V78cnKYHOWiPl4jIgF7Nk+Q7PAJDGa5pp8e97": {
                "chainKey": {
                  "counter": -1,
                  "key": "ga+NgKJeZKp3LB524mP40EUMwttmYXOiaUe6t2PAgx0="
                },
                "chainType": 1,
                "messageKeys": {}
              }
            },
            "pendingPreKey": {
              "signedKeyId": 1,
              "baseKey": "BUlms/vaznAzm10/n491ycIAERQd/8ihjwiUFZjle21o",
              "preKeyId": 376
            }
          },
          "BcwDNG3a1h5VyfYOWHud8UDUtJd1AMYyCG7doR5mWesW": {
            "registrationId": 68,
            "currentRatchet": {
              "ephemeralKeyPair": {
                "pubKey": "BcF8EgVK4B9mb5LKd8npV1eYLbydvXdPtTKco4QHdVkb",
                "privKey": "2FtsDv2GDAvcIh2/Bz4cHenz8K1jP9qRNQ9ZIWHe8mo="
              },
              "lastRemoteEphemeralKey": "Be8MN2rLegMkYMvzhatGJanubgVPPKYQTFm7qE9wjsos",
              "previousCounter": 0,
              "rootKey": "qrY9Oj+ptXWfI4Sr4CQx9XIawRlmFG+FZBoMYJ0zEV4="
            },
            "indexInfo": {
              "baseKey": "BcwDNG3a1h5VyfYOWHud8UDUtJd1AMYyCG7doR5mWesW",
              "baseKeyType": 1,
              "closed": 1658387463423,
              "used": 1658387462917,
              "created": 1658387462917,
              "remoteIdentityKey": "BXpCX1ShydItbg7yCbF3q1YuJ4YOGZuXdApPvnwzjC14"
            },
            "_chains": {
              "BcF8EgVK4B9mb5LKd8npV1eYLbydvXdPtTKco4QHdVkb": {
                "chainKey": {
                  "counter": -1,
                  "key": "PUHR71L69sKieczEH+ek6JPx3EoJeMN3HcAbIxxqF4I="
                },
                "chainType": 1,
                "messageKeys": {}
              }
            },
            "pendingPreKey": {
              "signedKeyId": 1,
              "baseKey": "BcwDNG3a1h5VyfYOWHud8UDUtJd1AMYyCG7doR5mWesW",
              "preKeyId": 385
            }
          },
          "Ba6GBhAUD2o8y8KS3YHDm/NK7RrT9/IjUdPycHgemkk6": {
            "registrationId": 68,
            "currentRatchet": {
              "ephemeralKeyPair": {
                "pubKey": "BRNicX/vnU/wAMUi4mkl/OnxTDUtFG6+RA7C1GuVa0pi",
                "privKey": "QJc/psUA/Byd12wSm5WjLkAFU/RFSDHubW81JNKX71s="
              },
              "lastRemoteEphemeralKey": "Be8MN2rLegMkYMvzhatGJanubgVPPKYQTFm7qE9wjsos",
              "previousCounter": 0,
              "rootKey": "SI7FluTYfYvz2jMp6dRdlHP7qDuL1i8Pg6SeNU+aBAg="
            },
            "indexInfo": {
              "baseKey": "Ba6GBhAUD2o8y8KS3YHDm/NK7RrT9/IjUdPycHgemkk6",
              "baseKeyType": 1,
              "closed": 1658387463633,
              "used": 1658387463400,
              "created": 1658387463400,
              "remoteIdentityKey": "BXpCX1ShydItbg7yCbF3q1YuJ4YOGZuXdApPvnwzjC14"
            },
            "_chains": {
              "BRNicX/vnU/wAMUi4mkl/OnxTDUtFG6+RA7C1GuVa0pi": {
                "chainKey": {
                  "counter": -1,
                  "key": "TPybw//BRpbmr8UeCZb6nK31DPkKeTx6EnwqvyyWh+A="
                },
                "chainType": 1,
                "messageKeys": {}
              }
            },
            "pendingPreKey": {
              "signedKeyId": 1,
              "baseKey": "Ba6GBhAUD2o8y8KS3YHDm/NK7RrT9/IjUdPycHgemkk6",
              "preKeyId": 369
            }
          },
          "BdRECwKIQN5Q4jDygrcx8HZiuJHGH7kqCU67VlpmZ/pH": {
            "registrationId": 68,
            "currentRatchet": {
              "ephemeralKeyPair": {
                "pubKey": "BZcuE37Y+uQIVFaCiJOzhYYiBfLSV0CXx7sqc6krpQVH",
                "privKey": "cIlb7XkiU+6qqNkzGu6zTecyNukDiC4hryd5STeZjEA="
              },
              "lastRemoteEphemeralKey": "Be8MN2rLegMkYMvzhatGJanubgVPPKYQTFm7qE9wjsos",
              "previousCounter": 0,
              "rootKey": "pIXgpoL0cQy/246JL64Ndcwr545/SmFwmAZpBmCxLVA="
            },
            "indexInfo": {
              "baseKey": "BdRECwKIQN5Q4jDygrcx8HZiuJHGH7kqCU67VlpmZ/pH",
              "baseKeyType": 1,
              "closed": 1658387464111,
              "used": 1658387463602,
              "created": 1658387463602,
              "remoteIdentityKey": "BXpCX1ShydItbg7yCbF3q1YuJ4YOGZuXdApPvnwzjC14"
            },
            "_chains": {
              "BZcuE37Y+uQIVFaCiJOzhYYiBfLSV0CXx7sqc6krpQVH": {
                "chainKey": {
                  "counter": -1,
                  "key": "J1Vlt646KCYY0WUNn/2DtcBfvV1nfuEvRw0HjfclbzI="
                },
                "chainType": 1,
                "messageKeys": {}
              }
            },
            "pendingPreKey": {
              "signedKeyId": 1,
              "baseKey": "BdRECwKIQN5Q4jDygrcx8HZiuJHGH7kqCU67VlpmZ/pH",
              "preKeyId": 397
            }
          },
          "Bda91XGfh+/ERiMERsfkHpqkNQcHaeum5yJPdJatuZgd": {
            "registrationId": 68,
            "currentRatchet": {
              "ephemeralKeyPair": {
                "pubKey": "BUVn8zY181oWA2MMPAp7WL9ZyI5UO4tSYQ30hmBb95R9",
                "privKey": "YKXbP3XmVue8Ir9gkbfqLbzqdP65+KrqXnn5wBP/EGY="
              },
              "lastRemoteEphemeralKey": "Be8MN2rLegMkYMvzhatGJanubgVPPKYQTFm7qE9wjsos",
              "previousCounter": 0,
              "rootKey": "8jUybFFcSm9R0TPlcSpKTRhlEzOUb6suLO4bWYfCRqw="
            },
            "indexInfo": {
              "baseKey": "Bda91XGfh+/ERiMERsfkHpqkNQcHaeum5yJPdJatuZgd",
              "baseKeyType": 1,
              "closed": 1658387464296,
              "used": 1658387464085,
              "created": 1658387464085,
              "remoteIdentityKey": "BXpCX1ShydItbg7yCbF3q1YuJ4YOGZuXdApPvnwzjC14"
            },
            "_chains": {
              "BUVn8zY181oWA2MMPAp7WL9ZyI5UO4tSYQ30hmBb95R9": {
                "chainKey": {
                  "counter": -1,
                  "key": "N1xGE6z1D0Gmq/IG5ft6R8zZZbbSHtE5mnxu9cvZ5QY="
                },
                "chainType": 1,
                "messageKeys": {}
              }
            },
            "pendingPreKey": {
              "signedKeyId": 1,
              "baseKey": "Bda91XGfh+/ERiMERsfkHpqkNQcHaeum5yJPdJatuZgd",
              "preKeyId": 387
            }
          },
          "BSRH6huB7kk6uu0nNcmH8iG7+4zDpOsbX1WSL2Ff0IIi": {
            "registrationId": 68,
            "currentRatchet": {
              "ephemeralKeyPair": {
                "pubKey": "BThW6Dapet6CXHCtAnIhVm/5fc0R6hovlF0sPwaHioAq",
                "privKey": "8FA18Y1d+gONR2tofygfkMv09REtJh2Z9q+7sIQYAE8="
              },
              "lastRemoteEphemeralKey": "Be8MN2rLegMkYMvzhatGJanubgVPPKYQTFm7qE9wjsos",
              "previousCounter": 0,
              "rootKey": "hED+z0mv16ycYfpfkNMeioSLJaTv8r7hCa507FRg4vQ="
            },
            "indexInfo": {
              "baseKey": "BSRH6huB7kk6uu0nNcmH8iG7+4zDpOsbX1WSL2Ff0IIi",
              "baseKeyType": 1,
              "closed": 1658387464782,
              "used": 1658387464278,
              "created": 1658387464278,
              "remoteIdentityKey": "BXpCX1ShydItbg7yCbF3q1YuJ4YOGZuXdApPvnwzjC14"
            },
            "_chains": {
              "BThW6Dapet6CXHCtAnIhVm/5fc0R6hovlF0sPwaHioAq": {
                "chainKey": {
                  "counter": -1,
                  "key": "i3WwdMHrzhVHwkIPqQdUmvVFjZs2wXoj23ZTWS/DBWA="
                },
                "chainType": 1,
                "messageKeys": {}
              }
            },
            "pendingPreKey": {
              "signedKeyId": 1,
              "baseKey": "BSRH6huB7kk6uu0nNcmH8iG7+4zDpOsbX1WSL2Ff0IIi",
              "preKeyId": 373
            }
          },
          "BT5bmHiAJjsKEacCUjLGc2iDrpb7mcg56nJ3i5HrA75v": {
            "registrationId": 68,
            "currentRatchet": {
              "ephemeralKeyPair": {
                "pubKey": "BQDVlexJl6RDA+bWTZTt85WeHRmeZC5KBuPL5zqCNDh7",
                "privKey": "8Eiq3yD5JdIc671cfnQr5tV5Z+osno8i2lMWoh737Xc="
              },
              "lastRemoteEphemeralKey": "Be8MN2rLegMkYMvzhatGJanubgVPPKYQTFm7qE9wjsos",
              "previousCounter": 0,
              "rootKey": "OQgFchOtV8Oj/cYYfiyl9w6GGdyjU9umsWqlxWGRxvM="
            },
            "indexInfo": {
              "baseKey": "BT5bmHiAJjsKEacCUjLGc2iDrpb7mcg56nJ3i5HrA75v",
              "baseKeyType": 1,
              "closed": 1658387465063,
              "used": 1658387464751,
              "created": 1658387464751,
              "remoteIdentityKey": "BXpCX1ShydItbg7yCbF3q1YuJ4YOGZuXdApPvnwzjC14"
            },
            "_chains": {
              "BQDVlexJl6RDA+bWTZTt85WeHRmeZC5KBuPL5zqCNDh7": {
                "chainKey": {
                  "counter": 0,
                  "key": "lufB+S/z0zS5tsnH3XH+gekpLESVYP86X20T38SBX1c="
                },
                "chainType": 1,
                "messageKeys": {}
              }
            },
            "pendingPreKey": {
              "signedKeyId": 1,
              "baseKey": "BT5bmHiAJjsKEacCUjLGc2iDrpb7mcg56nJ3i5HrA75v",
              "preKeyId": 384
            }
          },
          "BYfPcIMoIZZQfrT0zKxvuj0QNCkpRwzmGkpurql73vgz": {
            "registrationId": 68,
            "currentRatchet": {
              "ephemeralKeyPair": {
                "pubKey": "Bbq7zs7cy5tY0PnuKRQMUtejYVB6SsxQs6JswACwSuhd",
                "privKey": "YHA1Vc+rCRHdzQEToNv4j1eG8i9zO6MIunQA4gxZQE8="
              },
              "lastRemoteEphemeralKey": "Be8MN2rLegMkYMvzhatGJanubgVPPKYQTFm7qE9wjsos",
              "previousCounter": 0,
              "rootKey": "Jijzf8YnPzbZMsuOf3JghyEmQN6HMLUoNXTmjM4/ALM="
            },
            "indexInfo": {
              "baseKey": "BYfPcIMoIZZQfrT0zKxvuj0QNCkpRwzmGkpurql73vgz",
              "baseKeyType": 1,
              "closed": 1658387465238,
              "used": 1658387465041,
              "created": 1658387465041,
              "remoteIdentityKey": "BXpCX1ShydItbg7yCbF3q1YuJ4YOGZuXdApPvnwzjC14"
            },
            "_chains": {
              "Bbq7zs7cy5tY0PnuKRQMUtejYVB6SsxQs6JswACwSuhd": {
                "chainKey": {
                  "counter": -1,
                  "key": "2ysRxaDWaeaOdCdOb+q19bUx3PcCaAMbvjmxaJdfQcs="
                },
                "chainType": 1,
                "messageKeys": {}
              }
            },
            "pendingPreKey": {
              "signedKeyId": 1,
              "baseKey": "BYfPcIMoIZZQfrT0zKxvuj0QNCkpRwzmGkpurql73vgz",
              "preKeyId": 381
            }
          },
          "BXO+xNFb/ckRmYYgAD1Jp7D2Gx/gnMV3H5wTKV1Uzbop": {
            "registrationId": 68,
            "currentRatchet": {
              "ephemeralKeyPair": {
                "pubKey": "BcEjE49QZrEjOzUHlD8UaLAssnGVVH66NL254Y6H8K9R",
                "privKey": "AJyOruT5ekAQvheTXIYF3JkI0dxzNkU33CN2dylu9m0="
              },
              "lastRemoteEphemeralKey": "Be8MN2rLegMkYMvzhatGJanubgVPPKYQTFm7qE9wjsos",
              "previousCounter": 0,
              "rootKey": "OpSSh5fyLPDBXbPANZoqfJG7zqqoMUhkiJx6droSFlQ="
            },
            "indexInfo": {
              "baseKey": "BXO+xNFb/ckRmYYgAD1Jp7D2Gx/gnMV3H5wTKV1Uzbop",
              "baseKeyType": 1,
              "closed": 1658387465565,
              "used": 1658387465215,
              "created": 1658387465215,
              "remoteIdentityKey": "BXpCX1ShydItbg7yCbF3q1YuJ4YOGZuXdApPvnwzjC14"
            },
            "_chains": {
              "BcEjE49QZrEjOzUHlD8UaLAssnGVVH66NL254Y6H8K9R": {
                "chainKey": {
                  "counter": -1,
                  "key": "4VQZjNWXpCnyILkFOwufnzGfOtyAZIo6XrWLCZl2lgw="
                },
                "chainType": 1,
                "messageKeys": {}
              }
            },
            "pendingPreKey": {
              "signedKeyId": 1,
              "baseKey": "BXO+xNFb/ckRmYYgAD1Jp7D2Gx/gnMV3H5wTKV1Uzbop",
              "preKeyId": 374
            }
          },
          "Bcc38+jTE3xy61rWTjmpCIlRduUlJ5typCayEiz0aXVR": {
            "registrationId": 68,
            "currentRatchet": {
              "ephemeralKeyPair": {
                "pubKey": "BUc3BEhA6xiytCpV3NR+uM69y8exP1gaHBP0MtUNAy4/",
                "privKey": "ILM06YCpdwBOFpOJXSY3n+/7p2HHPn7/WeeaVbwQiXE="
              },
              "lastRemoteEphemeralKey": "Be8MN2rLegMkYMvzhatGJanubgVPPKYQTFm7qE9wjsos",
              "previousCounter": 0,
              "rootKey": "zgnFWUmrKeL/PKzxTitP5auQUXYxsr8FOfChXNFJfgs="
            },
            "indexInfo": {
              "baseKey": "Bcc38+jTE3xy61rWTjmpCIlRduUlJ5typCayEiz0aXVR",
              "baseKeyType": 1,
              "closed": 1658387466126,
              "used": 1658387465541,
              "created": 1658387465541,
              "remoteIdentityKey": "BXpCX1ShydItbg7yCbF3q1YuJ4YOGZuXdApPvnwzjC14"
            },
            "_chains": {
              "BUc3BEhA6xiytCpV3NR+uM69y8exP1gaHBP0MtUNAy4/": {
                "chainKey": {
                  "counter": -1,
                  "key": "JQWvwQ28e20JU+1tOEnRJO9Vj020nggPRa1bK8KM5+0="
                },
                "chainType": 1,
                "messageKeys": {}
              }
            },
            "pendingPreKey": {
              "signedKeyId": 1,
              "baseKey": "Bcc38+jTE3xy61rWTjmpCIlRduUlJ5typCayEiz0aXVR",
              "preKeyId": 372
            }
          },
          "BdyqolG7tKEtpxe1wtpmEQVjGAQJWTDG++g+1WU9p65u": {
            "registrationId": 68,
            "currentRatchet": {
              "ephemeralKeyPair": {
                "pubKey": "BeZLUlc1evrEguuh7Cbv4RStcz+174V84hLpnwtiCgtx",
                "privKey": "sHwjZga8F9REJy4UVQo5C5l/AxK46eh1+gwsgb766UA="
              },
              "lastRemoteEphemeralKey": "Be8MN2rLegMkYMvzhatGJanubgVPPKYQTFm7qE9wjsos",
              "previousCounter": 0,
              "rootKey": "T4ysJ75XCaM+OHe1wTL8tOFHAPlpRx5xQ7JmMiKok3Q="
            },
            "indexInfo": {
              "baseKey": "BdyqolG7tKEtpxe1wtpmEQVjGAQJWTDG++g+1WU9p65u",
              "baseKeyType": 1,
              "closed": 1658387466586,
              "used": 1658387466100,
              "created": 1658387466100,
              "remoteIdentityKey": "BXpCX1ShydItbg7yCbF3q1YuJ4YOGZuXdApPvnwzjC14"
            },
            "_chains": {
              "BeZLUlc1evrEguuh7Cbv4RStcz+174V84hLpnwtiCgtx": {
                "chainKey": {
                  "counter": -1,
                  "key": "xwpyncqRXdzzNDrFD3ycGTip1fRyHfui2yMCw93NrrY="
                },
                "chainType": 1,
                "messageKeys": {}
              }
            },
            "pendingPreKey": {
              "signedKeyId": 1,
              "baseKey": "BdyqolG7tKEtpxe1wtpmEQVjGAQJWTDG++g+1WU9p65u",
              "preKeyId": 380
            }
          },
          "BWqBpaPdQnxRpVRQvlbtqB6jiVefjoU7o4z/OnLPyiBr": {
            "registrationId": 68,
            "currentRatchet": {
              "ephemeralKeyPair": {
                "pubKey": "BXvoyjaYnrYe2aGxL+7aYIQ7VDFXvNYLs4vISY4Vle8R",
                "privKey": "sFS921oVkznqYUfr6mX3oKH/e7XhXHJSz6XvzJ+tXlo="
              },
              "lastRemoteEphemeralKey": "Be8MN2rLegMkYMvzhatGJanubgVPPKYQTFm7qE9wjsos",
              "previousCounter": 0,
              "rootKey": "sDATnSi4tYkXqpEx/hlF0ZpjPTtIGqu74g/ZseRWl7E="
            },
            "indexInfo": {
              "baseKey": "BWqBpaPdQnxRpVRQvlbtqB6jiVefjoU7o4z/OnLPyiBr",
              "baseKeyType": 1,
              "closed": 1658387467079,
              "used": 1658387466568,
              "created": 1658387466568,
              "remoteIdentityKey": "BXpCX1ShydItbg7yCbF3q1YuJ4YOGZuXdApPvnwzjC14"
            },
            "_chains": {
              "BXvoyjaYnrYe2aGxL+7aYIQ7VDFXvNYLs4vISY4Vle8R": {
                "chainKey": {
                  "counter": -1,
                  "key": "Rr05kS8gNtOJaCfaSWC3HLmwttM1hDa1vXFk8EmiTZg="
                },
                "chainType": 1,
                "messageKeys": {}
              }
            },
            "pendingPreKey": {
              "signedKeyId": 1,
              "baseKey": "BWqBpaPdQnxRpVRQvlbtqB6jiVefjoU7o4z/OnLPyiBr",
              "preKeyId": 377
            }
          },
          "BSt5A1UmuOzSge7miNll6+dFlo5NzClUwmDUUBDvo6RB": {
            "registrationId": 68,
            "currentRatchet": {
              "ephemeralKeyPair": {
                "pubKey": "BemGzt7p/m7kaJeGijX8dJG0Wvdv4ZjJtS8M8sGlz/MZ",
                "privKey": "APHJO/j94/Q/ojuGTkWUvst235Vs7dT7hwIs9h658mM="
              },
              "lastRemoteEphemeralKey": "Be8MN2rLegMkYMvzhatGJanubgVPPKYQTFm7qE9wjsos",
              "previousCounter": 0,
              "rootKey": "r/YhwleqndWohSdLMznKsNiUUod/neBXwX4gvFyBnLA="
            },
            "indexInfo": {
              "baseKey": "BSt5A1UmuOzSge7miNll6+dFlo5NzClUwmDUUBDvo6RB",
              "baseKeyType": 1,
              "closed": 1658387467578,
              "used": 1658387467055,
              "created": 1658387467055,
              "remoteIdentityKey": "BXpCX1ShydItbg7yCbF3q1YuJ4YOGZuXdApPvnwzjC14"
            },
            "_chains": {
              "BemGzt7p/m7kaJeGijX8dJG0Wvdv4ZjJtS8M8sGlz/MZ": {
                "chainKey": {
                  "counter": -1,
                  "key": "z99TFnSc52j25ycsJCYcSfqlJncFuTvbCO9xS9mu7Vc="
                },
                "chainType": 1,
                "messageKeys": {}
              }
            },
            "pendingPreKey": {
              "signedKeyId": 1,
              "baseKey": "BSt5A1UmuOzSge7miNll6+dFlo5NzClUwmDUUBDvo6RB",
              "preKeyId": 388
            }
          },
          "BQyBXKQAu6evaoo2Th+waq4BJ9GTh3nUZq/0GIptLfsb": {
            "registrationId": 68,
            "currentRatchet": {
              "ephemeralKeyPair": {
                "pubKey": "BbexV3g8y1x9SOoBCaJ/Vpyux9hwISJth1+8kjWwHJNx",
                "privKey": "UPE0WLVC9r1pVawsG0C1LoTPC/xvMV4gaUA2gxt8sX8="
              },
              "lastRemoteEphemeralKey": "Be8MN2rLegMkYMvzhatGJanubgVPPKYQTFm7qE9wjsos",
              "previousCounter": 0,
              "rootKey": "+0/m3tDtzSZZnO5t6SSrUXxGW+b7tYtlJkm52XQntu4="
            },
            "indexInfo": {
              "baseKey": "BQyBXKQAu6evaoo2Th+waq4BJ9GTh3nUZq/0GIptLfsb",
              "baseKeyType": 1,
              "closed": 1658387468036,
              "used": 1658387467557,
              "created": 1658387467557,
              "remoteIdentityKey": "BXpCX1ShydItbg7yCbF3q1YuJ4YOGZuXdApPvnwzjC14"
            },
            "_chains": {
              "BbexV3g8y1x9SOoBCaJ/Vpyux9hwISJth1+8kjWwHJNx": {
                "chainKey": {
                  "counter": -1,
                  "key": "08/Yf5XP0lTlYIFYRD1yPcunSMhSVLQPjnOVt1z/El0="
                },
                "chainType": 1,
                "messageKeys": {}
              }
            },
            "pendingPreKey": {
              "signedKeyId": 1,
              "baseKey": "BQyBXKQAu6evaoo2Th+waq4BJ9GTh3nUZq/0GIptLfsb",
              "preKeyId": 379
            }
          },
          "BSi94ndYEMaA8zUFyQkFZkWQ0P1gwFm8ABVC3twdrzlE": {
            "registrationId": 68,
            "currentRatchet": {
              "ephemeralKeyPair": {
                "pubKey": "BQOBevdTwFD3BILnxLgDlxpXICjzkz9WK20HefGgCRdi",
                "privKey": "6F5TivJ2h7Vzcu7d6p6l/IB8EEje+xGEo97e77wQIXg="
              },
              "lastRemoteEphemeralKey": "Be8MN2rLegMkYMvzhatGJanubgVPPKYQTFm7qE9wjsos",
              "previousCounter": 0,
              "rootKey": "/sywMDXPY5I44ZUqKz7WY5aPqbGaVNVpYZ/jXzewP38="
            },
            "indexInfo": {
              "baseKey": "BSi94ndYEMaA8zUFyQkFZkWQ0P1gwFm8ABVC3twdrzlE",
              "baseKeyType": 1,
              "closed": 1658387468622,
              "used": 1658387468019,
              "created": 1658387468019,
              "remoteIdentityKey": "BXpCX1ShydItbg7yCbF3q1YuJ4YOGZuXdApPvnwzjC14"
            },
            "_chains": {
              "BQOBevdTwFD3BILnxLgDlxpXICjzkz9WK20HefGgCRdi": {
                "chainKey": {
                  "counter": 0,
                  "key": "j48zmDJP0nV2C8+vmYixXozLg2ObqmkCK8apHllOLzE="
                },
                "chainType": 1,
                "messageKeys": {}
              }
            },
            "pendingPreKey": {
              "signedKeyId": 1,
              "baseKey": "BSi94ndYEMaA8zUFyQkFZkWQ0P1gwFm8ABVC3twdrzlE",
              "preKeyId": 395
            }
          },
          "BTp4r2gRZH4IF/6dDNm8vCc3hDhIu+DWc7qOGeiF2jNP": {
            "registrationId": 68,
            "currentRatchet": {
              "ephemeralKeyPair": {
                "pubKey": "BShgTOkGtcVuncgVNO+aze4ZBhkKRk9HwMY3XCLDYQgg",
                "privKey": "4O46qILCujcgExrh60ExcKY2umlcqDzXdPrrznenYEM="
              },
              "lastRemoteEphemeralKey": "Be8MN2rLegMkYMvzhatGJanubgVPPKYQTFm7qE9wjsos",
              "previousCounter": 0,
              "rootKey": "XdNP/UR4Qa+9Dzb/Iw0CMLWV+QB6DWJN70CXNkDOfac="
            },
            "indexInfo": {
              "baseKey": "BTp4r2gRZH4IF/6dDNm8vCc3hDhIu+DWc7qOGeiF2jNP",
              "baseKeyType": 1,
              "closed": 1658387469105,
              "used": 1658387468603,
              "created": 1658387468603,
              "remoteIdentityKey": "BXpCX1ShydItbg7yCbF3q1YuJ4YOGZuXdApPvnwzjC14"
            },
            "_chains": {
              "BShgTOkGtcVuncgVNO+aze4ZBhkKRk9HwMY3XCLDYQgg": {
                "chainKey": {
                  "counter": -1,
                  "key": "7x99+w4/Ml91nKerrFM5nnLtSYBprCWn68KdQ4UKyEE="
                },
                "chainType": 1,
                "messageKeys": {}
              }
            },
            "pendingPreKey": {
              "signedKeyId": 1,
              "baseKey": "BTp4r2gRZH4IF/6dDNm8vCc3hDhIu+DWc7qOGeiF2jNP",
              "preKeyId": 382
            }
          },
          "BcJUlqgRZ5uXYOC5MxODUE8g2x4/sQUnVGfodHxYNQ5v": {
            "registrationId": 68,
            "currentRatchet": {
              "ephemeralKeyPair": {
                "pubKey": "BWu+TfFVuj33OnDqqlmX3E+fn13dFkgO/0+oNpygcMBz",
                "privKey": "WLJYewVpLf1AiJRvF8FnL6CAj9H4neI6DQDMF9T8f2s="
              },
              "lastRemoteEphemeralKey": "Be8MN2rLegMkYMvzhatGJanubgVPPKYQTFm7qE9wjsos",
              "previousCounter": 0,
              "rootKey": "8EKS+Q+mFHz7d/5dWh2THdyfqr5vIwbJrSjhVhN31Bw="
            },
            "indexInfo": {
              "baseKey": "BcJUlqgRZ5uXYOC5MxODUE8g2x4/sQUnVGfodHxYNQ5v",
              "baseKeyType": 1,
              "closed": 1658387469579,
              "used": 1658387469086,
              "created": 1658387469086,
              "remoteIdentityKey": "BXpCX1ShydItbg7yCbF3q1YuJ4YOGZuXdApPvnwzjC14"
            },
            "_chains": {
              "BWu+TfFVuj33OnDqqlmX3E+fn13dFkgO/0+oNpygcMBz": {
                "chainKey": {
                  "counter": -1,
                  "key": "zqBebKdVnNE7Q7DhLZwwX3jF6fVZgfIzBM/Uu0/t66s="
                },
                "chainType": 1,
                "messageKeys": {}
              }
            },
            "pendingPreKey": {
              "signedKeyId": 1,
              "baseKey": "BcJUlqgRZ5uXYOC5MxODUE8g2x4/sQUnVGfodHxYNQ5v",
              "preKeyId": 390
            }
          },
          "Bfwip0hPPgdG8DVGvgWX50VJfYz2E5NBYE7V23qeDOhC": {
            "registrationId": 68,
            "currentRatchet": {
              "ephemeralKeyPair": {
                "pubKey": "BdV3LAE/tKhQ5L7wlf76jmZzs4jUYZi6EDMsZfgjSWdb",
                "privKey": "IJyC0454r6Sqkh7RrxwwmTlfwfMtqIRmYLy+T/pIym4="
              },
              "lastRemoteEphemeralKey": "Be8MN2rLegMkYMvzhatGJanubgVPPKYQTFm7qE9wjsos",
              "previousCounter": 0,
              "rootKey": "UlLPn9sGa8AGJiYqcwchPLDdqju1DSu0scWvjRYd7ls="
            },
            "indexInfo": {
              "baseKey": "Bfwip0hPPgdG8DVGvgWX50VJfYz2E5NBYE7V23qeDOhC",
              "baseKeyType": 1,
              "closed": -1,
              "used": 1658387469557,
              "created": 1658387469557,
              "remoteIdentityKey": "BXpCX1ShydItbg7yCbF3q1YuJ4YOGZuXdApPvnwzjC14"
            },
            "_chains": {
              "BdV3LAE/tKhQ5L7wlf76jmZzs4jUYZi6EDMsZfgjSWdb": {
                "chainKey": {
                  "counter": 8,
                  "key": "inMC24ZAzNn6yhZZhoNK2F889BxFoX49CGIJCFnOvZg="
                },
                "chainType": 1,
                "messageKeys": {}
              }
            },
            "pendingPreKey": {
              "signedKeyId": 1,
              "baseKey": "Bfwip0hPPgdG8DVGvgWX50VJfYz2E5NBYE7V23qeDOhC",
              "preKeyId": 386
            }
          }
        },
        "version": "v1"
      },
      "6285878075754.0": {
        "_sessions": {
          "BS3JEsNWGz/CJWctmBRyb0BDM55TNR3VnFm/AVTCvKpC": {
            "registrationId": 302935355,
            "currentRatchet": {
              "ephemeralKeyPair": {
                "pubKey": "BT1Vd0Jg5UJRyErhHD+L5goSp3qvtXEK4eokyzVMB9h9",
                "privKey": "cCbC9pEy921UZ/3x75Jth4O6TwyJX3Sbt1xQ4HQbukU="
              },
              "lastRemoteEphemeralKey": "BfcGbgGwz2qASoVlbGcz9Y/YOj6Akk2737H9ez9Sl3FE",
              "previousCounter": 0,
              "rootKey": "7nY3SixgDUWbFKMsnKXjCohlSXLyenAL8stkppJ9240="
            },
            "indexInfo": {
              "baseKey": "BS3JEsNWGz/CJWctmBRyb0BDM55TNR3VnFm/AVTCvKpC",
              "baseKeyType": 2,
              "closed": -1,
              "used": 1658387700258,
              "created": 1658320152050,
              "remoteIdentityKey": "BUfMNVFKEeisoUw21o/WIHM2jYh3FaGglDFGmGU5QQ0J"
            },
            "_chains": {
              "BU+OyIWBDifkfcpyOkD9jaStbVek3KRL/4p4a+GGnoor": {
                "chainKey": {
                  "counter": 0
                },
                "chainType": 2,
                "messageKeys": {}
              },
              "BduDsV8Fuw/AUQROWkjdH864l8j3lbbtUIYd5iKXvBQ+": {
                "chainKey": {
                  "counter": 0
                },
                "chainType": 2,
                "messageKeys": {}
              },
              "BX6qlUhiXg3WB/ayQm/WySL9RGForhb9LzSacvOWQtJM": {
                "chainKey": {
                  "counter": 0
                },
                "chainType": 2,
                "messageKeys": {}
              },
              "BWrFHVSRERKgDGUzZ3ArzFrxhDraT4yq0O52RQYgXM1j": {
                "chainKey": {
                  "counter": 2
                },
                "chainType": 2,
                "messageKeys": {}
              },
              "BaGo2Gg4yokAAiQrUmm+17sCvEr2YwnAGGmiJNe/xbxK": {
                "chainKey": {
                  "counter": 0
                },
                "chainType": 2,
                "messageKeys": {}
              },
              "BQZp9AYq/128ZC//C5LDzDCkY4n56efBaplN0numgSxk": {
                "chainKey": {
                  "counter": 6
                },
                "chainType": 2,
                "messageKeys": {
                  "0": "pAdPdngjjc1tCNVZl9ivf2dpOvLQAWPIdfx8eYysgi8=",
                  "1": "6tNXg7kRnSfygsuvW6EoQ86FlpF79H4md2kJ6NT1eMY="
                }
              },
              "BWU2+Lg5t119stljzsotpRP+L3qLx/lsXtI2ROiMuIUC": {
                "chainKey": {
                  "counter": 0
                },
                "chainType": 2,
                "messageKeys": {}
              },
              "BcUOcTW5WL1BuLIw8NBM03sZqTUPareeo3rGmSB0fJwv": {
                "chainKey": {
                  "counter": 3
                },
                "chainType": 2,
                "messageKeys": {
                  "0": "ddcHQ1xOx1S6RzcoekbIHlonIJhHC3dehlUDeF2LrSY=",
                  "1": "B7r8zfVyKkN0HMRQSTgbLe7Yl88J/Vwg08TRn53XSfk="
                }
              },
              "BX1Ay+7kFw+feb+Unn+BVYg5hg67LvzWgdHipAV6dIVS": {
                "chainKey": {
                  "counter": 1
                },
                "chainType": 2,
                "messageKeys": {
                  "0": "ctDleBfPJB4DyYL99FvZnlSl1FSLtgFbfeVEJ0wC0Ks="
                }
              },
              "Ber4vcd3RaLM+wmp0CKW9fglx1n1udac3qGohNLmcgB+": {
                "chainKey": {
                  "counter": 0
                },
                "chainType": 2,
                "messageKeys": {}
              },
              "BZUc24xFoJ758X3XK9Q7to/hZs3gwlvHVB09j8RabHRA": {
                "chainKey": {
                  "counter": 3
                },
                "chainType": 2,
                "messageKeys": {
                  "3": "mKlWThLQEsk4pmWM8kRmPdzP+7/E0xalp5p6ToeopL0="
                }
              },
              "BW1vTfSDFTgnpMrrHFVTG1oj0Q2Q860cohxRDtUHJJkX": {
                "chainKey": {
                  "counter": 0
                },
                "chainType": 2,
                "messageKeys": {}
              },
              "BWVvvjs8iYdsTslJZ06ftDQo8cSo8ooG8anttKWygI5h": {
                "chainKey": {
                  "counter": 0
                },
                "chainType": 2,
                "messageKeys": {}
              },
              "BRw6RsYCXooEfB4Oasdw6f/kVqtuCntWaeBwrRNFz10b": {
                "chainKey": {
                  "counter": 4
                },
                "chainType": 2,
                "messageKeys": {
                  "0": "A9XEvLFy3eINRE7mGYMou+b9bdOrMRf0k1F7f/eH8jE="
                }
              },
              "BeCAy7VtVwM18AH5zFIh9sDh9nR/CKVVRK16mNkWSDID": {
                "chainKey": {
                  "counter": 0
                },
                "chainType": 2,
                "messageKeys": {}
              },
              "BfcGbgGwz2qASoVlbGcz9Y/YOj6Akk2737H9ez9Sl3FE": {
                "chainKey": {
                  "counter": 1,
                  "key": "yb0FOviWNll2YXoaKgAbU3xWLTUI+JG5zt7q6cu/TF8="
                },
                "chainType": 2,
                "messageKeys": {}
              },
              "BT1Vd0Jg5UJRyErhHD+L5goSp3qvtXEK4eokyzVMB9h9": {
                "chainKey": {
                  "counter": 3,
                  "key": "lctCOjnvpe810UyKu0O/JWOl56WVxjd2RCmkPj7g5dw="
                },
                "chainType": 1,
                "messageKeys": {}
              }
            }
          }
        },
        "version": "v1"
      },
      "6285773400911.0": {
        "_sessions": {
          "BY1RelgH+qFpa+s7oervdWPHwWfLQUevmBcxRi5ejxsi": {
            "registrationId": 538358393,
            "currentRatchet": {
              "ephemeralKeyPair": {
                "pubKey": "Bf2PoN/BCuZQ146z0uzFel116lmhR1Zvv8Yh0WMwjMw9",
                "privKey": "EL46edmh16BJTkJA04AT+mVBKYcxVjRlgegjvhLmAHg="
              },
              "lastRemoteEphemeralKey": "BeK2hc8lMpom7InWL88WSXNM7jXKCyueZOPowkjquXIi",
              "previousCounter": 0,
              "rootKey": "OviwQxSNwcagD/L3Tnrfcn4QI9hV56RcHUVS5H/PWSg="
            },
            "indexInfo": {
              "baseKey": "BY1RelgH+qFpa+s7oervdWPHwWfLQUevmBcxRi5ejxsi",
              "baseKeyType": 2,
              "closed": -1,
              "used": 1658320282717,
              "created": 1658320282717,
              "remoteIdentityKey": "BQ8EIU3M5dc90Idq96Is4VQl6r05oYT40NMRyne0qqBq"
            },
            "_chains": {
              "BeK2hc8lMpom7InWL88WSXNM7jXKCyueZOPowkjquXIi": {
                "chainKey": {
                  "counter": 0,
                  "key": "poliPPyj7cGZ8WMjZ+gcu88kuGNZCsa913cPBU0kI3Q="
                },
                "chainType": 2,
                "messageKeys": {}
              },
              "Bf2PoN/BCuZQ146z0uzFel116lmhR1Zvv8Yh0WMwjMw9": {
                "chainKey": {
                  "counter": -1,
                  "key": "HrE2OQ4+5aSEhjTp782NbKSZI+KqQugJ1xfjB+MpIlA="
                },
                "chainType": 1,
                "messageKeys": {}
              }
            }
          }
        },
        "version": "v1"
      },
      "6288740030517.0": {
        "_sessions": {
          "BemzEFdn921HjphjrjtvSAfSOtDHJ4b6ACjAb3qVG793": {
            "registrationId": 921933869,
            "currentRatchet": {
              "ephemeralKeyPair": {
                "pubKey": "BRbGg/GWrvYkrP0zyBaELu+X8/JWAT/TtzrdHP/uOksZ",
                "privKey": "OMRyWWD6kBKrshyB5Cf2Isaxy3QiqIIhixhdLlybKGY="
              },
              "lastRemoteEphemeralKey": "BcjHVfU8Lnjv3HlQI94nTGxTICF68M9mkGoaOFrRomZ7",
              "previousCounter": 0,
              "rootKey": "z4M/e9Oy25rKLSVUJwEObUnpvtD7bhEPML3vIHCGryw="
            },
            "indexInfo": {
              "baseKey": "BemzEFdn921HjphjrjtvSAfSOtDHJ4b6ACjAb3qVG793",
              "baseKeyType": 2,
              "closed": -1,
              "used": 1658359112048,
              "created": 1658359112048,
              "remoteIdentityKey": "BdGq+g8BRKduUCEy+5kSeuAuDY4648DFnMQMSTFnIo50"
            },
            "_chains": {
              "BcjHVfU8Lnjv3HlQI94nTGxTICF68M9mkGoaOFrRomZ7": {
                "chainKey": {
                  "counter": 0,
                  "key": "F1mBHEXN2R27mahqTttC/OOBk5cV783L2dSKutq7Zdw="
                },
                "chainType": 2,
                "messageKeys": {}
              },
              "BRbGg/GWrvYkrP0zyBaELu+X8/JWAT/TtzrdHP/uOksZ": {
                "chainKey": {
                  "counter": -1,
                  "key": "Vc85RQ//CLWpC3HtSzRez5WbECNg5Q9MPywAruiqRwo="
                },
                "chainType": 1,
                "messageKeys": {}
              }
            }
          }
        },
        "version": "v1"
      },
      "62881037052224.0": {
        "_sessions": {
          "BRMjomczIqYPqx1sgae2AVQEUuHOTh+ZdAnUwUWaTqg+": {
            "registrationId": 1396521768,
            "currentRatchet": {
              "ephemeralKeyPair": {
                "pubKey": "BXe9nzKjK4LuX4Ne2OaNvipM5+oRWB2gyyqA0K97Tnle",
                "privKey": "aEp5r/PoaiIoMGy3mSH6ESPmzTWy8Reg+K4P23sXxmw="
              },
              "lastRemoteEphemeralKey": "BRJutKNyMdF/rXylPxqCo3BkTmO0fe/H3SujgVTLYxg+",
              "previousCounter": 0,
              "rootKey": "nWm1cQAsr99uCKmbtHsLfBzDV3yEQs+J0bPnpVDfQTw="
            },
            "indexInfo": {
              "baseKey": "BRMjomczIqYPqx1sgae2AVQEUuHOTh+ZdAnUwUWaTqg+",
              "baseKeyType": 2,
              "closed": -1,
              "used": 1658359112087,
              "created": 1658359112087,
              "remoteIdentityKey": "BYUeZUH5opYrROfG/qKS50SrmW1OjapzMV2VblBxpfMn"
            },
            "_chains": {
              "BRJutKNyMdF/rXylPxqCo3BkTmO0fe/H3SujgVTLYxg+": {
                "chainKey": {
                  "counter": 11,
                  "key": "xfcyzgdDuF59sl+VxMGh+A4cO8P9vjizSKENbPPEuZI="
                },
                "chainType": 2,
                "messageKeys": {
                  "3": "xi5POeK8qo5eiH858fFLeW1VuxLUnlZvLjIHufLJz9I=",
                  "5": "nxjdwnu2UrBNzom8UekDLby2rAk4UntXcBTvH/NRF0M=",
                  "10": "0JZMGmeIoi3G9Ky7BHA8/A+TWkkinNkLXGd/aFWF48c="
                }
              },
              "BXe9nzKjK4LuX4Ne2OaNvipM5+oRWB2gyyqA0K97Tnle": {
                "chainKey": {
                  "counter": -1,
                  "key": "cJWyaJK+NAhGno9YIouO7OGyu9zhxJHM9ZyCVtureAA="
                },
                "chainType": 1,
                "messageKeys": {}
              }
            }
          }
        },
        "version": "v1"
      },
      "6285821080627.0": {
        "_sessions": {
          "BW12UOCludBq4QiwX1FrYKFKVvG9aY5Pp622u1ti9pkc": {
            "registrationId": 1615834091,
            "currentRatchet": {
              "ephemeralKeyPair": {
                "pubKey": "BevexTQod3ddXzwDBaz9hCZjmDVWwUWJqBhKttUKYPZm",
                "privKey": "0DN7J6DFW76E3bhNSzAR1KkSB27F3kmYxMYgn7Ui4GE="
              },
              "lastRemoteEphemeralKey": "BacLWeYBv9VfznaX4B95VE3aFCAgqfHciwg4qbbjA7h7",
              "previousCounter": 0,
              "rootKey": "JHr8IMuubSNd0XG+NWA6+nrI8FkaN8Ee3DdMYaxqM4k="
            },
            "indexInfo": {
              "baseKey": "BW12UOCludBq4QiwX1FrYKFKVvG9aY5Pp622u1ti9pkc",
              "baseKeyType": 2,
              "closed": -1,
              "used": 1658359112121,
              "created": 1658359112121,
              "remoteIdentityKey": "BZ+cLyuSoo8by7cdDFxDmqLLjAmrTrlZo+9CfzDtfGFa"
            },
            "_chains": {
              "BacLWeYBv9VfznaX4B95VE3aFCAgqfHciwg4qbbjA7h7": {
                "chainKey": {
                  "counter": 0,
                  "key": "Ud22GBZB/zCG9MqYh2dB8Bf8X/wRIYJMffUAAeBFCO8="
                },
                "chainType": 2,
                "messageKeys": {}
              },
              "BevexTQod3ddXzwDBaz9hCZjmDVWwUWJqBhKttUKYPZm": {
                "chainKey": {
                  "counter": -1,
                  "key": "LXITzYTuy+F6haLJolNPoj6bn8y69sGCYL3/q/HOHLc="
                },
                "chainType": 1,
                "messageKeys": {}
              }
            }
          }
        },
        "version": "v1"
      },
      "6285353429957.0": {
        "_sessions": {
          "BaSNVjoldL2sU+pIfnrxfNRa+/eIEbMgpglGrgvehVkL": {
            "registrationId": 231966427,
            "currentRatchet": {
              "ephemeralKeyPair": {
                "pubKey": "BZ14U2IuNI7Jo65CVKu97yEgefQArQhvNskGSyaIx4l+",
                "privKey": "8MAty4HVatNl8asP66apuqmeDiet1oyvRkn2qRYIQkQ="
              },
              "lastRemoteEphemeralKey": "BabZSZpCWMTuC4K4/+lsGYJtvD9oydl4eUVFjaaZBH0U",
              "previousCounter": 0,
              "rootKey": "MrK0Msi370wPiN0iIQAWaqWa6Vwi2yrKSUYjMKCUYzg="
            },
            "indexInfo": {
              "baseKey": "BaSNVjoldL2sU+pIfnrxfNRa+/eIEbMgpglGrgvehVkL",
              "baseKeyType": 2,
              "closed": -1,
              "used": 1658359112156,
              "created": 1658359112156,
              "remoteIdentityKey": "BQpcsIZwBeVfinz6UnZJpF826iPB29I3sOL87OhmqXpu"
            },
            "_chains": {
              "BabZSZpCWMTuC4K4/+lsGYJtvD9oydl4eUVFjaaZBH0U": {
                "chainKey": {
                  "counter": 3,
                  "key": "q+zCECTV9zQF6wjIgtWoe6/c5OYo9YM3pJcI8lb64QQ="
                },
                "chainType": 2,
                "messageKeys": {}
              },
              "BZ14U2IuNI7Jo65CVKu97yEgefQArQhvNskGSyaIx4l+": {
                "chainKey": {
                  "counter": -1,
                  "key": "fLRr/4lqlB8DzzrwQ1j8Ub71uWhWkOjnilqk/h6qGgM="
                },
                "chainType": 1,
                "messageKeys": {}
              }
            }
          }
        },
        "version": "v1"
      },
      "6281524379040.0": {
        "_sessions": {
          "BS28Oj10FwDmXBjsJmeZO8USFvmRABlsRu9lZuQyXf99": {
            "registrationId": 376291411,
            "currentRatchet": {
              "ephemeralKeyPair": {
                "pubKey": "BVCdYwuBt5Q1NN041rQMhQCBe8TOI8PA3HOQpORD2zAl",
                "privKey": "OMqZ5bdN2FqAMXC7HthHC1/HmZTGZ31NruZmP4xP314="
              },
              "lastRemoteEphemeralKey": "Bfs7ZRK0zT7/p8qnACeX7u62QZxmpwvdXb9thR5WbLYo",
              "previousCounter": 0,
              "rootKey": "OT6ko0qM2Vtsw/6ZP7M8/rT2RZb27rTlHAdByxsqGcE="
            },
            "indexInfo": {
              "baseKey": "BS28Oj10FwDmXBjsJmeZO8USFvmRABlsRu9lZuQyXf99",
              "baseKeyType": 2,
              "closed": -1,
              "used": 1658359112191,
              "created": 1658359112191,
              "remoteIdentityKey": "Bb7JKa7U8Ln7yze6M9CXo0x/21v3XDpAKmRB44kYTuZH"
            },
            "_chains": {
              "Bfs7ZRK0zT7/p8qnACeX7u62QZxmpwvdXb9thR5WbLYo": {
                "chainKey": {
                  "counter": 0,
                  "key": "z3Sf5rdybJQ6Wn44J7IN/kdafBAaTCmbLk9QAIF8axE="
                },
                "chainType": 2,
                "messageKeys": {}
              },
              "BVCdYwuBt5Q1NN041rQMhQCBe8TOI8PA3HOQpORD2zAl": {
                "chainKey": {
                  "counter": -1,
                  "key": "f9DCdQfGLlIR3oj+q4Xa4lPTd7Tu7lL3FeD2BEfoiE4="
                },
                "chainType": 1,
                "messageKeys": {}
              }
            }
          }
        },
        "version": "v1"
      },
      "6287738331591.0": {
        "_sessions": {
          "BUu4ysR3/6zqO/vrVUnczuzZ2brlnzQnOMJ2PN83O9J7": {
            "registrationId": 1544060295,
            "currentRatchet": {
              "ephemeralKeyPair": {
                "pubKey": "BfAi2bErSxbe+paGkMA975/RDnFj1oJZC7/U6epucwkx",
                "privKey": "6MKO6d/J1l0J0j/2N+QSrq0zufj/VP1ZURdXBG4HmnE="
              },
              "lastRemoteEphemeralKey": "BYbUdOPCWFJT7gev1EAzSZ1yrkIkzrtXw8hIp6ArzGZY",
              "previousCounter": 0,
              "rootKey": "IEzmjBVRDaVzJFVN7P2WZQxP+1kGa2eRsirmWgolBRo="
            },
            "indexInfo": {
              "baseKey": "BUu4ysR3/6zqO/vrVUnczuzZ2brlnzQnOMJ2PN83O9J7",
              "baseKeyType": 2,
              "closed": -1,
              "used": 1658387461191,
              "created": 1658387461191,
              "remoteIdentityKey": "BV4qcmmt0I22yU7t78583Ap9Eown5oGTE/qnoYVZekJr"
            },
            "_chains": {
              "BYbUdOPCWFJT7gev1EAzSZ1yrkIkzrtXw8hIp6ArzGZY": {
                "chainKey": {
                  "counter": 1,
                  "key": "MrlAoCSVK42V/E5TvkecGZNyrTtiLNV9unWiHb5vLWM="
                },
                "chainType": 2,
                "messageKeys": {}
              },
              "BfAi2bErSxbe+paGkMA975/RDnFj1oJZC7/U6epucwkx": {
                "chainKey": {
                  "counter": -1,
                  "key": "P2566FeCsfP+qsu+tmbUBDC3n9BUI0luv5WY7mrbdgo="
                },
                "chainType": 1,
                "messageKeys": {}
              }
            }
          }
        },
        "version": "v1"
      },
      "6283834558105.0": {
        "_sessions": {
          "Bar6nqIxlw7gss5QpaRyuRMNTndyYX7y/n4qKQT6oN9r": {
            "registrationId": 661088590,
            "currentRatchet": {
              "ephemeralKeyPair": {
                "pubKey": "Bdw5rruiRp0SgfHdl6qg6r9Dtjx2JNl/jyZ4wLCSw54D",
                "privKey": "mJZMktZogY4nKXcSfUQc8RRtIuQli7fwA+6G+HgE828="
              },
              "lastRemoteEphemeralKey": "BXbBY4bsYj2IThtzYUMHC9NXABfX7ibbOFZOMmwOb41v",
              "previousCounter": 0,
              "rootKey": "2D4stUfOQsp8DDUb5LNVcldMhks3Ih5KrQNZCn36h1c="
            },
            "indexInfo": {
              "baseKey": "Bar6nqIxlw7gss5QpaRyuRMNTndyYX7y/n4qKQT6oN9r",
              "baseKeyType": 2,
              "closed": -1,
              "used": 1658387461231,
              "created": 1658387461231,
              "remoteIdentityKey": "BcAQhrmAP1FicQAMJIxBX3qM2gvO1yeK2jj4ZHz5/2Em"
            },
            "_chains": {
              "BXbBY4bsYj2IThtzYUMHC9NXABfX7ibbOFZOMmwOb41v": {
                "chainKey": {
                  "counter": 3,
                  "key": "TrcKPVLe8qXLh4/riKUl96y6q4+sJ3pzQ08YP/WI42A="
                },
                "chainType": 2,
                "messageKeys": {
                  "0": "4djawEWEchu0LGTLb+78CiO31xeWcBLcUqlW++mpsEg=",
                  "1": "bKTnK1TEXLwnnHTHdQKtiOxj9u73SUsoEIBeP9iGs8w=",
                  "2": "vzqiyIdRzPXiH6lo8ZkTUjyEtvpuyiXN+gJxWXv7z1o="
                }
              },
              "Bdw5rruiRp0SgfHdl6qg6r9Dtjx2JNl/jyZ4wLCSw54D": {
                "chainKey": {
                  "counter": -1,
                  "key": "4rIerR5xzLKqHUMUr7cpE24kcrvDAmg61NcjC7cNOOU="
                },
                "chainType": 1,
                "messageKeys": {}
              }
            }
          }
        },
        "version": "v1"
      },
      "6289526217791.0": {
        "_sessions": {
          "BSBI4TaQL50Hb4k3HY4PfqIiDXlXsLPmh+H8reU0cyQF": {
            "registrationId": 105592766,
            "currentRatchet": {
              "ephemeralKeyPair": {
                "pubKey": "BaHsRfBI31d5hKO8h+OYKDe+lnxBLBrwuIHo6TiqJ8ts",
                "privKey": "kLeXiUn0pmYu2EiTrAREaz5JaQnU+JT/CL95GLVCIkE="
              },
              "lastRemoteEphemeralKey": "BeYhgNvAPKbobJVX1p0W63fnAWRKcNusFAdAYK3XjyMJ",
              "previousCounter": 3,
              "rootKey": "43r6Ug5G+9U5mM+JZz+A4k1scQH7bCOgSJVc9jwn+jc="
            },
            "indexInfo": {
              "baseKey": "BSBI4TaQL50Hb4k3HY4PfqIiDXlXsLPmh+H8reU0cyQF",
              "baseKeyType": 1,
              "closed": -1,
              "used": 1658387782005,
              "created": 1658387706381,
              "remoteIdentityKey": "BQNsYJQJ1AMqN0ycJjtsOL2KCuykv0ZsN6xzenpgMfki"
            },
            "_chains": {
              "BeYhgNvAPKbobJVX1p0W63fnAWRKcNusFAdAYK3XjyMJ": {
                "chainKey": {
                  "counter": 0,
                  "key": "Hm9zQPrN7yIaPgjHY6E4M1OILaNQw//GTml0QnCb2fw="
                },
                "chainType": 2,
                "messageKeys": {}
              },
              "BaHsRfBI31d5hKO8h+OYKDe+lnxBLBrwuIHo6TiqJ8ts": {
                "chainKey": {
                  "counter": -1,
                  "key": "K80uHrXwLVC6EBl5iRvUcR88REUBoB9GKIMpGK/kP4k="
                },
                "chainType": 1,
                "messageKeys": {}
              }
            }
          }
        },
        "version": "v1"
      },
      "6289693024351.0": {
        "_sessions": {
          "BQLe/zsUqFBx5HDtTj8GyDKGjev0YEbzlC/oEntC/bsI": {
            "registrationId": 948243259,
            "currentRatchet": {
              "ephemeralKeyPair": {
                "pubKey": "BWakmRaHf+fkLpoWnB1hcX5FUMO/HchcgxkGtBghOlMk",
                "privKey": "0CpfLx2lCPp82sb/hnW5CPL23JBJ8yebhDtxbt+tW34="
              },
              "lastRemoteEphemeralKey": "BV3l+RdklKSZpinDABxVOiVImUAISXn7I0JVkubNG556",
              "previousCounter": 0,
              "rootKey": "cArfpCaWXey2eEz38s/ZShpHD0SGch46B7sM/ZlKl4c="
            },
            "indexInfo": {
              "baseKey": "BQLe/zsUqFBx5HDtTj8GyDKGjev0YEbzlC/oEntC/bsI",
              "baseKeyType": 2,
              "closed": -1,
              "used": 1658390769859,
              "created": 1658390769859,
              "remoteIdentityKey": "BYHiXCozfpub8v8ikODNqwJwgWNq98hDPKBihh8KAh8J"
            },
            "_chains": {
              "BV3l+RdklKSZpinDABxVOiVImUAISXn7I0JVkubNG556": {
                "chainKey": {
                  "counter": 0,
                  "key": "ndiNhtD8kS0IROJ428KVctyCnHJTU+hwNKSQtyJcvP0="
                },
                "chainType": 2,
                "messageKeys": {}
              },
              "BWakmRaHf+fkLpoWnB1hcX5FUMO/HchcgxkGtBghOlMk": {
                "chainKey": {
                  "counter": -1,
                  "key": "X0xb2oq2EJ6G/idILtqd6hr6oST15YpCQOIFxaR9ihg="
                },
                "chainType": 1,
                "messageKeys": {}
              }
            }
          }
        },
        "version": "v1"
      }
    },
    "appStateSyncKeys": {
      "AAAAAEbn": {
        "keyData": "Iui4ekGao+45kewAzfK4sjQ/DRGHR131F93RwB1ZC+M=",
        "fingerprint": {
          "rawId": 1837541533,
          "currentIndex": 1,
          "deviceIndexes": [
            0
          ]
        },
        "timestamp": "1657275898993"
      },
      "AAAAAEbo": {
        "keyData": "9XTzAWMfbmUvmCdfsRa3oLibVFR2yQf3SU3UJl5fE/8=",
        "fingerprint": {
          "rawId": 1837541534,
          "currentIndex": 1,
          "deviceIndexes": [
            0,
            1
          ]
        },
        "timestamp": "1657285567304"
      },
      "AAAAAEbl": {
        "keyData": "VccLFNG76W/epchg39XhSB4ipi4wD3QU2TNqLNqIW/Y=",
        "fingerprint": {
          "rawId": 4294967295,
          "currentIndex": 4294967295,
          "deviceIndexes": [
            0
          ]
        },
        "timestamp": "1657204700919"
      },
      "AAAAAEbm": {
        "keyData": "rHjUL9dXUorNkt5bVnklbBWHZ01mTLjPw5EKa8ioHMw=",
        "fingerprint": {
          "rawId": 1837541533,
          "currentIndex": 1,
          "deviceIndexes": [
            0,
            1
          ]
        },
        "timestamp": "0"
      }
    },
    "appStateVersions": {
      "critical_unblock_low": {
        "version": 37,
        "hash": {
          "type": "Buffer",
          "data": "Lxnl+gFfE0lZYI5TPv5WCAd6wH8en4UrwuHTs+GbZYBICeUvJPirTvapzwamJu0CflRZWaRt7hTlMM0biOfmnNhbsW50BIkIH1uBRz2W/6NS6Ded+SaTd2BG/nEVOB9KMJm6IdXmsS2VgfLAYX7P3K+AcFShtSNi88lgCIBit6A="
        },
        "indexValueMap": {
          "AiEwtqI29/TPRNec3NTLrHfZwFOh9Bq9ZRnGH7RUw6U=": {
            "valueMac": {
              "type": "Buffer",
              "data": "GtAffYQUH8iBVJsJbWi/Ag207MJ+/SaadRf/JSnYyMw="
            }
          },
          "B6bHQgfvYzFfXmUwLS7zZ1Zpm+ceYGQGrzD36w37y8g=": {
            "valueMac": {
              "type": "Buffer",
              "data": "ZDu9ABrovn8ojRdvvGkkoPqRs31K55fEeeGEZGg2MmI="
            }
          },
          "DSHJydqxeyWGoVCVZ3q8JHXZqkdE3kmuwWQ+PDSAWT4=": {
            "valueMac": {
              "type": "Buffer",
              "data": "1KWABxcCQDsC+b2HJsqHbuo05nO/EsCe2CBumRaltas="
            }
          },
          "FbaVbuD9GDeb6NFZkdmO8NoNz1hM+8UE0pm86pDQhjs=": {
            "valueMac": {
              "type": "Buffer",
              "data": "yT6GVHBfy4Y3j1qlGKUTmuUorV28f/l2IDm+bnjJuEs="
            }
          },
          "HLvLVwbBpGabPzeB1xD5BZmQS9N6gf4j9lb1gUsi3Qc=": {
            "valueMac": {
              "type": "Buffer",
              "data": "HBniUChwjSqV2NRtESidtD/Hf3w/5dPGVfBnH7AHqIA="
            }
          },
          "LFzhMpUgXP7uPTSAOyHpeNMVzMWnZFVOXq5AAM5waII=": {
            "valueMac": {
              "type": "Buffer",
              "data": "cNnHookEN3tJTSq16+xxm30Xo6WE6n6hhM3gss/Q2j0="
            }
          },
          "L/U7c9YrI4NOHQk6YTdACv30LABJOzhQqTRvytozwUw=": {
            "valueMac": {
              "type": "Buffer",
              "data": "vwwcFBTP7qaMiI2Ve6TJazPg3TJWLPW7ox+Q7uSUUMk="
            }
          },
          "S9MB6Z0V1imITdysjkTfHkaAgVK8vpYJfikFQocLthQ=": {
            "valueMac": {
              "type": "Buffer",
              "data": "ZjnsDeR1zHR3cngSPaKmPsQQsuqfs3/SLCDts6hQ+vg="
            }
          },
          "TZk+9aWZsLqbtpJgj0YhK+ectS1V0o5yHQGj0IdwrZA=": {
            "valueMac": {
              "type": "Buffer",
              "data": "8dm9050ISX7XoaLy13cA2FF7SeeqYCx41vZO6Nv1wc8="
            }
          },
          "VHrViRy7GwimswgNrTOt0y00+V+rt3V0c/JwuX62T3g=": {
            "valueMac": {
              "type": "Buffer",
              "data": "UXju8GCHw+EcrHTTliVAPuBub14SqhkCkREGK3EC/DA="
            }
          },
          "VkUJfXfuYLBfYovVNhIxxw7DUsqdpKP+wPES8EcDQmc=": {
            "valueMac": {
              "type": "Buffer",
              "data": "hQjOQDFO+CD41/r1sFH7dKW8NGpfa3v3lJrzlfoNN20="
            }
          },
          "VkzTx3BOzjV9SKehbD7V+7YoVS8ZdqRIn5lY+E4VPN4=": {
            "valueMac": {
              "type": "Buffer",
              "data": "u2IUobscnM3yhAniltOOIcs/1bla4R6j/IJzdya+eeI="
            }
          },
          "VumS/YwNmM8tGS7CBeixl60BAkuU0Sa2BUzqhgbj3Og=": {
            "valueMac": {
              "type": "Buffer",
              "data": "kPa5xawMcEMS+q1tgXL85CbhcuP6WlJ8e0CtP1n9TU8="
            }
          },
          "XxY65Dg4bvwMGBGTATfas6YuJQ+R5BkVzeBh7Himx3U=": {
            "valueMac": {
              "type": "Buffer",
              "data": "/tknTiIqDwt+CKYRyaBUq8nD9J81fBnkjyqquRn+83U="
            }
          },
          "dP0W5Pz1jAoJNGZO0xyAh4HS831suGQj7z3QCYB5Hlk=": {
            "valueMac": {
              "type": "Buffer",
              "data": "spwHyNy1rXU/uhXi71FEy4WdXuUUQR7N7T3b5ILOiLQ="
            }
          },
          "j9npSqAuwuQf999KdXG8WsWWmd7wNUtCfpR+DpOSFPI=": {
            "valueMac": {
              "type": "Buffer",
              "data": "JpfApXxu7FCW6txBSNI1Fw8cjD3mZb/wMlQuSmeKhck="
            }
          },
          "kIVATT2B9l/SQ3EuCUTRTI7NDolNeEV8I+3pMCiwmWA=": {
            "valueMac": {
              "type": "Buffer",
              "data": "RY+YOEWtaVOwnttzOSdcvaRMy71RrM8m9NH14xSOoZk="
            }
          },
          "qCCB2QPr+m08bvsCKud6YRNk8v1R4KwNkpEWZpaFghk=": {
            "valueMac": {
              "type": "Buffer",
              "data": "FZ9hDRxRThqWBlrsHOrpwUp5CczOEf7TQJc9SaZk+48="
            }
          },
          "q1JN9xYgEm7FXZSMeOlH1Jkp8r+EnZI2E/JRvw7ZWkI=": {
            "valueMac": {
              "type": "Buffer",
              "data": "gpwg/5ei8QEzET6wrA7d1qir076jIpv07X05sCXfNVw="
            }
          },
          "rqq1R05cCpGUmTqv2AHGoM5MuF0ORM3KsOOsD5mY4Co=": {
            "valueMac": {
              "type": "Buffer",
              "data": "oKeoah7vhp8W+jEeEKNe/EPmRc7tVWQeGfJYa0VE0nU="
            }
          },
          "tr9gBMAN/tUWZ/4cNUbcUoAYZLCFPwRf4Ixk/nD6RYc=": {
            "valueMac": {
              "type": "Buffer",
              "data": "87UjAVRViBepcyw5ls1WT9qVuk4M56DjDdtz2gpdIeA="
            }
          },
          "vPjt2PeuRZS7RtAGxCDzO7b5sxafdpXm3FbSuX9m+0k=": {
            "valueMac": {
              "type": "Buffer",
              "data": "SPUrkSazNWrA4FcTyOKqVs3Dm0SYc7iRQ25PPu0JtqE="
            }
          },
          "xL88WVN1V2ZjO5KXhvLLMQoG28GObQfmfD5ineNPYJU=": {
            "valueMac": {
              "type": "Buffer",
              "data": "wu+VKD+fuJEr0xvtSrSGLiTXD7qRb8sr9dBwLREOAgE="
            }
          },
          "yzqmOK00tZLWHQ6O8KzKA3Pkl6qFTUFg92Sz9aXEKYw=": {
            "valueMac": {
              "type": "Buffer",
              "data": "99PXkJFTl7XdxR/y5uKo+hQ65wzCF/XAGOSQBjY6c3E="
            }
          },
          "1/4ChvjipU0+Nc0Y1qKVROi9uR3RsOfXCzem677KfXY=": {
            "valueMac": {
              "type": "Buffer",
              "data": "P6pfGnwV7x9vxfcm2gwBcrRJ3PP9Ueszd05y5Dbebv0="
            }
          },
          "2BMYdImCgbeDxQfTLt+c4t0ol9bSk9AE7MyCf/g8ufs=": {
            "valueMac": {
              "type": "Buffer",
              "data": "Sayce4SyYcqyKsII4I6ryEF+tj+I88U+po9AGlkvQuY="
            }
          },
          "6evBtk4HZmQaK19Fa7gGaED2uz4WWoNCZdUvAY0dDug=": {
            "valueMac": {
              "type": "Buffer",
              "data": "3NZ6/bLS3VZeuRUR/HLP42kUCeDm6vAWTaXcp81HlJw="
            }
          },
          "9fGMOGvTuQKDB2Xy36KXnWMPUtGuOEcqzJQ/ZBq7ni8=": {
            "valueMac": {
              "type": "Buffer",
              "data": "ySXRLsMALO5byOLQ7ILKtFClwgsMFBwAqwabZf/So44="
            }
          },
          "+CaEVhrnmmqRwDASZM4YhZDifJODRsuXB1U36IF+zzA=": {
            "valueMac": {
              "type": "Buffer",
              "data": "ptxLquNvdV8t23wca3oFB6aWSlQNh/VxmsYWSOnXPDk="
            }
          },
          "5g6WZpxhofTetRPhgfMycTL3+0BGin2uuXN5i/jTGK0=": {
            "valueMac": {
              "type": "Buffer",
              "data": "Q9k7FuBhVaBN8qZEdRpGM6ZXvcGhA/nNDGygEuoOIIU="
            }
          },
          "N3GYsa6NNHF16QuYDrUHB4Q6ab14yYiG1ZSkfTaYgYY=": {
            "valueMac": {
              "type": "Buffer",
              "data": "TarFhh3onfc2Wz3o3dK3sgX3BN0AY0uGoYJvkbNetq4="
            }
          },
          "RaseKmuOfRPA1jkXcLUl9Ow5wMisSLs+J+oGYtrPm80=": {
            "valueMac": {
              "type": "Buffer",
              "data": "eZdjaZ6NKuW1hjxaX/1yxoMoi6Y5lyK/bKfZS7w5HLo="
            }
          },
          "sofEDCjqfKXXnDBlt8yhz0JpNL+LRzuIOOSb6N5o2sk=": {
            "valueMac": {
              "type": "Buffer",
              "data": "q56iLFwvf3kGmJrsRlTsfoUi3OXhpA4H+1Um9ZCWGIM="
            }
          },
          "r9iZtqFAs7t664I+wr5Ry3zak1NZMhSGdplzJiOnTyk=": {
            "valueMac": {
              "type": "Buffer",
              "data": "y1Al46G5a3HlDTrBGlcqqPxvimvhRpmW761kbC8ylCc="
            }
          },
          "61p0hCWwGe8lVI4QQoLd1fXnKIdBINOlpBsJA/uluwM=": {
            "valueMac": {
              "type": "Buffer",
              "data": "L6H8Lv/AhN2nbdMXgT/upJJNw1O+jhTZDYy25aV/auU="
            }
          }
        }
      },
      "regular_high": {
        "version": 24,
        "hash": {
          "type": "Buffer",
          "data": "4sDA8xJDjDsiWjWukObe83p3/ICqSKIubPCLQWkFLK5eiMiOKIQJUdAzg3g+4tYc4q6Z0CcWGucSlXIUBa/gRrxxpc7Echn15RJoEsOr9zibYNHhJU5sUbvl2oTenyD8ExmimZe25I0B3IA5K7abJaew7E1EPtr5zkXKSpvrg+c="
        },
        "indexValueMap": {
          "ADTwkd47bUanyZ1oW0m3CYVthboCVOu5BwFsOJtxGZs=": {
            "valueMac": {
              "type": "Buffer",
              "data": "Zs72DsWGbjWHRnXC6M/Wm8R1myukMyT9aGDmF86nMj8="
            }
          },
          "GjJUU2HNS1EGUqN2PkwB5qH/5uCS1m8TIMVe0vs0gCQ=": {
            "valueMac": {
              "type": "Buffer",
              "data": "w4ZywZMXtHv1igDY+NdP7VNLdVS+mFqg/G9fykSi0KQ="
            }
          },
          "IST6tVa9OusG8ldSJ1vAdiWHJMhjv3DhB2nWBEIvg3Q=": {
            "valueMac": {
              "type": "Buffer",
              "data": "ghqI04GwoPF6FDNVrZPJwYiosFCOmrcvDM2GPBb3do4="
            }
          },
          "JAOz7YLa91daP2R/MRUiAcnkSNEYSU9l1lxV5+2df5Y=": {
            "valueMac": {
              "type": "Buffer",
              "data": "v7F/OF258ntdfCQvV5NAV+zc4Ya9LgFTIWoDrssJg9o="
            }
          },
          "JFRGjw5x1PvJo6pjyW8uYQD834UJMnWXJ18aS1I71xM=": {
            "valueMac": {
              "type": "Buffer",
              "data": "xCm7TTHSFTg/j/P+KH4qliPjY0iMLrgXbKhGkGX7n1k="
            }
          },
          "JSdiSo8PbMCPqp/9RjwSARAlC1yEVC74vcVr649fCWY=": {
            "valueMac": {
              "type": "Buffer",
              "data": "Pou33OxNy26NWcdrv/I9RB2TrW7PIPbYSUk8yTMHZTU="
            }
          },
          "Jp3RAtR0A+vf0ASQLVNfs/hE2mR3i1mUB29IeMT1xAE=": {
            "valueMac": {
              "type": "Buffer",
              "data": "GB/nQpnNOdMjS3cp3u2CHuz9j4PZNluTJHPSLLmS+gM="
            }
          },
          "KkS1iuTeFlFsIMN1VL8bFpEBQBG72bCezIte8Nxmf3U=": {
            "valueMac": {
              "type": "Buffer",
              "data": "IBc9otKMD6YW80HI7XOjaxxtsuvKL0PiZ2mp3jcMOm4="
            }
          },
          "Mb0LDoSK5cvJku6HxPBxzRg+W3aTncMhUIQS3BJE5CU=": {
            "valueMac": {
              "type": "Buffer",
              "data": "KjTPUioUfkD0DlYj7jcKMm37p7EjwzlkCxe6FXaRPo4="
            }
          },
          "PXDEpYTI90X5YAj1kfezV8OjFuXTn57iLqiK6QNwKwY=": {
            "valueMac": {
              "type": "Buffer",
              "data": "exiPWTM1mJy9yoza48aQjuW+uexYUTo/N9dROxEFR0g="
            }
          },
          "QoRF2zR3cx2MTwej4hRLF8wJ/QEeV76LwCcdIB11CCc=": {
            "valueMac": {
              "type": "Buffer",
              "data": "Qy2ojTPvzUzWSW3Pj1yXYrToY6KqVl8ZYlW8Y+ZQ+zo="
            }
          },
          "Q28YdGr9JdwafG2t7GIpESPqIKqbj0zXfofbGcFVOKc=": {
            "valueMac": {
              "type": "Buffer",
              "data": "25W5gPuZmMSt0e+39X9SYoPJLBfiq/wEqqgV1dTtF6c="
            }
          },
          "WpijqxErcHGXR6MepVCkiHw3pGZFDK6O/Gh205+zcT4=": {
            "valueMac": {
              "type": "Buffer",
              "data": "+Upmg7/B+CgpSf8FxmrGVnZHoFxj7HpdPROUEdO8uGo="
            }
          },
          "XOBnVsbaZAY85jQvOPaQOf8W4C3ZtGTiJ9iNEaD7PMU=": {
            "valueMac": {
              "type": "Buffer",
              "data": "ZHgutfcmbt6zL7ssd+ZEXI8YzUyqQpBWGw9p9Ca7Z34="
            }
          },
          "aer9GpbZCJU4tCjA4wwI5LWJY2gAorAOmpGfYA27Xb8=": {
            "valueMac": {
              "type": "Buffer",
              "data": "z4diXFjcuLKAVnNqGfM0R8n0WC1wsCIodMKIFUDd5Q4="
            }
          },
          "bo7ldmACxF2q4Qfobi0jWLq9DaHjnxJe7oJ5+h7kolc=": {
            "valueMac": {
              "type": "Buffer",
              "data": "jCLV7mXgTCLxBf73k2O/eQ13IcIgEzds/PxzhUp9r3s="
            }
          },
          "eLXn0wk2AND2439MRqizJZzGd50A2djVQ6wTIC3YwRM=": {
            "valueMac": {
              "type": "Buffer",
              "data": "onAl6a4No7TcL64BJpMR7c80Ys1SID+qs9+e4hOgsAY="
            }
          },
          "jgWdW7m4wYpVCzkxBSl3TmXQQZ5O3nysqi+VrqrPkOk=": {
            "valueMac": {
              "type": "Buffer",
              "data": "LGxcPcRaA/zgqBrp4bQXSBid4JnzuGnlnv/3n4119Y0="
            }
          },
          "kXZWSUoPArYDzA0wXVFvr9Ur4wt1+tQDEAJt04rGbjE=": {
            "valueMac": {
              "type": "Buffer",
              "data": "lx0vO/5s8n5is2wTYXFrE7/UQidqURKtpzEFhv99Hoo="
            }
          },
          "pyNVt9s7J/Zg7bqoNziuZBpdp4NeeiZzPLjf8hw3pTY=": {
            "valueMac": {
              "type": "Buffer",
              "data": "D5sVkaF4ob+YJoLAZt0I6pt4Ot+ARZwmqUq88Gav/IY="
            }
          },
          "qNJXLYnffdRgOd+iZdbi0VqUZuMYt14upV/HitfM/9E=": {
            "valueMac": {
              "type": "Buffer",
              "data": "gmof0XkI62HBOMWmzkcJn3p5mrBxN+4J6+7syW1CDfg="
            }
          },
          "qus+fNzm/qeLhL36sECpz+qa/VPMwRt+gDkCg9KT75w=": {
            "valueMac": {
              "type": "Buffer",
              "data": "WOHfIvfYl9edbunzvgO3t4SLnAcHxqIZ/20qDFndvPc="
            }
          },
          "udN6fNgU6xRW0rkn96lOSc2J/EL11kfQNcqMHsG7apo=": {
            "valueMac": {
              "type": "Buffer",
              "data": "DW0fjy1Zv4mzBJ475u67Wiq2wKfSGAJJqZJRlysGeWU="
            }
          },
          "wnI++P2QiYUEjZhXM+BLok/lein63Wqr0bnTaazEW0I=": {
            "valueMac": {
              "type": "Buffer",
              "data": "ZjtYApOBcYVWEC5mbZn3GTSZyYsEtxWEs6pEDtYGTxA="
            }
          },
          "w3xjVbvAlrQi+IrPqcxT0mfOZ5/HDL04Puk+OsCnykw=": {
            "valueMac": {
              "type": "Buffer",
              "data": "s7VMeVTeF8CPCpw0avhSWqe4TXlikAy4r5KS/hsRrNg="
            }
          },
          "1Nb4LNy3w8qweoynHuYVypOk51ydb1iINPQptdNOLpM=": {
            "valueMac": {
              "type": "Buffer",
              "data": "JfkC6YDYWDpFSv9SVqkUZx4KL9bef1W/NuODDVzh6Ns="
            }
          },
          "+7nxLZyR0vphq4BocjkPbJW9DjuVnPpaYYtwDCdLbTQ=": {
            "valueMac": {
              "type": "Buffer",
              "data": "cqaka09QYMNI2R7iy6ABr//MLLXc0FIMsrMv+Qpz9UU="
            }
          },
          "UEbuRFQrBlsT6SRQcBKoKmgVGjCR+KPaeRa/Gom01oc=": {
            "valueMac": {
              "type": "Buffer",
              "data": "F3I9dxllOJOpFowCmd8nRNKHKvHg0gwTzJz1TZfrLrc="
            }
          }
        }
      },
      "regular": {
        "version": 4,
        "hash": {
          "type": "Buffer",
          "data": "wOGZU1DZsMkHnbpOY7DtkSreV2ucrJ02JGbx8QgjrN00lLzVS09N8ssgJYA4OG6AsL6S/y2ZsVI2pyXoT2caaVwaDb0j+65upIqTv7R7igiT6hAp+HDP2gxmoNAVh6CGp7J2nM7m3VXCTENUEycNW9LbfKSXChO+1aB6uhXr97s="
        },
        "indexValueMap": {
          "Cg4uVdzOWSrB6WYm+vIBMQ8JNsrn6gA1r4kVgcVDrIw=": {
            "valueMac": {
              "type": "Buffer",
              "data": "ZSIWlRgfBxiQcYVjkpcYITULNOJsaoO3RT2CsL1SgSU="
            }
          },
          "LsOPbx04BGs51bFizjO3BN2B6jH9f76kB/JL77jKhZg=": {
            "valueMac": {
              "type": "Buffer",
              "data": "quVc/NLu37O+J8IKMijDGPqr6EeNaZ8DeBnAFkI9aak="
            }
          },
          "YuQLIXscR+H07wnCPH++t1DdirBzmXRoQcYxz8st2O0=": {
            "valueMac": {
              "type": "Buffer",
              "data": "+2vLDL5L9MiBFCLIkDmSzmQPaiQ/eeTXbVtO5G27IsU="
            }
          },
          "a1Bb7l8jTTseW30do1kIGg7aIOmAELZbiacDlBFFyu0=": {
            "valueMac": {
              "type": "Buffer",
              "data": "oqAmC0b/TrVQRsCUnZlPbgZR+sn9gw/6VtHUFumPJIU="
            }
          },
          "cfzpZ3MeotIvmsyttPSjpz0dKllD1SJUj1jxMFRY53w=": {
            "valueMac": {
              "type": "Buffer",
              "data": "gyWptsNu++dI2GpQ4Bupu+K5KBLntoqdOXMmvCMXxoo="
            }
          },
          "klR7cgtE8EuRilgh3w5iIg2BJCYbAJnd272yogNL8TE=": {
            "valueMac": {
              "type": "Buffer",
              "data": "6dxVlzzzo5WgdE6MSVleh3aBVTn2J6ZqKv8ysX890FI="
            }
          },
          "zh8YRd5GsunWlxnpoCgnwdH0rdid1E4ZwCbpeSYLkHw=": {
            "valueMac": {
              "type": "Buffer",
              "data": "kIMNxUetBm9gu6NXYcyXgkvDYsikP9an2TTMYO3hXgI="
            }
          },
          "5M8kzg2ah933t7Mn2wNwCIWGT0Q94f7A5tXQ2q+4HLA=": {
            "valueMac": {
              "type": "Buffer",
              "data": "3C6OaY5sCYl7P4XAB3HwviFwtcoPfXqf3F6EwuZ6FaU="
            }
          }
        }
      },
      "critical_block": {
        "version": 3,
        "hash": {
          "type": "Buffer",
          "data": "Fr4aGno/7PCHMh+6ZGLo8h9YaCoiHLSm/QtAqLShSIRDmTQLAbQayWRnMtpKGB9VmrwBgwzhwxvFcLAjzvMcbc4PLVBjRA9gsrjK5GZbsXR8fg0iYfoMxra7jlCQdVkMkRe4nwHaTCdqfaFUBQIraY43CagTcgHR+W4spjoVVXY="
        },
        "indexValueMap": {
          "dS4+pg0jkzue6Iq3lkdf/Gj4p0dQPTJRcz35e0z28To=": {
            "valueMac": {
              "type": "Buffer",
              "data": "z0wkNVUT8TenxHDkDF9x5qVa8Z/5K4bVepJJzNaYo7M="
            }
          },
          "isr0LRmWGfhhEXcDrbTjuio9HmGJhI+305KMZFZdHrc=": {
            "valueMac": {
              "type": "Buffer",
              "data": "fzU2N4EqxIlikgtcOj5HuVRIf4UYkjZNP678K5HqCgk="
            }
          },
          "i3+0rwsFcDr/hYoMo7S0Jh47ZzXw7g+fFCUTbvODgI0=": {
            "valueMac": {
              "type": "Buffer",
              "data": "HGm1CzYB5IaZWbxDm1gFvAo/568opWkixEeolYW7rxk="
            }
          }
        }
      },
      "regular_low": {
        "version": 8,
        "hash": {
          "type": "Buffer",
          "data": "MkVY+aQbISWX/mFk3BTgpAV8spobG3y3F0nkOMmnvDorf/nSKBBNOevWacD4z9traM1715/KAf9HmQAQOyk9F/Oc+OMzI7PAad3AEYqy0PNrd306dkNm6EcO51jd6cw5UcAZLUAB6PUrPZRXgnMbXPyT8cLk8X44ulFS0tpvAEE="
        },
        "indexValueMap": {
          "N9daoobEAK4MetUTMwWaHKFvqtkSabhuccjm0c3/994=": {
            "valueMac": {
              "type": "Buffer",
              "data": "MeAunQRi7jRdC3+AGEW2Bc2y039AKBGcjLnvXn9igzE="
            }
          },
          "OgOu4MgGga+KN1cMvgI6embAH02KDv9fvddR1SKMSns=": {
            "valueMac": {
              "type": "Buffer",
              "data": "PkuxjFtiK4+wxoho0HXuVDv6zztsYXTeGDris8vA0ZA="
            }
          },
          "PkZLIvVJveCW+Ar4xw+MKasS/FpXTpjfGi1hVd86InA=": {
            "valueMac": {
              "type": "Buffer",
              "data": "tZAHYSM6qZ/ij3TtACX8xhiTS9uesg6VB23sGjcrfks="
            }
          },
          "UADtT5lf3wxyEY0evdiyIV0ukV3DVFZV/07kkBy2UTA=": {
            "valueMac": {
              "type": "Buffer",
              "data": "FHw9uq5zGAqpQBnOzamLRDBvXieT8VwOkrBt2J5MqHU="
            }
          },
          "VuAdQBWG3UmO9LV45HrQLB/8TNCjouZqj5VH0uEZKNY=": {
            "valueMac": {
              "type": "Buffer",
              "data": "nORD68K6NaGUcZF7a4qF3mC6+hK114FrE8/cYvCxxxs="
            }
          },
          "Zo4DcGPugEi0Gkl8QkIWUW+zFm9qg6phOA7hynQYqb0=": {
            "valueMac": {
              "type": "Buffer",
              "data": "sPTOVtlDbnOpRWFWEeFSAIRPHrXDSEBZkVoNDB+sy+8="
            }
          },
          "m2ySnUw08KWupl2qCxi/BJVj/Vd5ubSI6IPXVH/nUTI=": {
            "valueMac": {
              "type": "Buffer",
              "data": "RFj7bnTaSFOYJqCUMVnSFGKp/k6+3ps24ZH1Wd1WX0g="
            }
          },
          "ojl2hEXmAZygii36E6bVWs4B4XeItHtrNmJMnDi4y7c=": {
            "valueMac": {
              "type": "Buffer",
              "data": "kfy3AldcVLUDQ4QbCeGmKsAVSiDGpEUsR1v2ueDm+B4="
            }
          },
          "pZWuamssI9SCyYma+LVpJ+LJ2SbmvAvKi4LPzSWgamo=": {
            "valueMac": {
              "type": "Buffer",
              "data": "YV4XiDf13XD5pEN+1yEcaqmNFhSrTKjNj/408OWQU68="
            }
          },
          "qUePu/TBM9PBnZUVol/nEHTubgFcanQW2z/YFO0yiZc=": {
            "valueMac": {
              "type": "Buffer",
              "data": "WlcHzqJbF2OMNLWol2dbHM+c7wA0yJ1bDEbdgmmGYQs="
            }
          },
          "zu+gj/XOvOZfyjq70KUk3NVY8qzmFycIsKnlVSgoJDE=": {
            "valueMac": {
              "type": "Buffer",
              "data": "w07U+S3My62Re0lP8a1PJkzGq19VgZG7WoscokJBV7Y="
            }
          },
          "0WL8DIFRgOhb9pkcwVqvBhjJarg59EHORw8ceczuExY=": {
            "valueMac": {
              "type": "Buffer",
              "data": "TiBr8k1VYrQz0uM+QENHXslRkaVgG16Xi7krdhUo6dg="
            }
          },
          "7RzHzJnVbEml7C/C8tRBcvkaC4YNpCxTW6sbBRmUYpU=": {
            "valueMac": {
              "type": "Buffer",
              "data": "mYG2gfkeZgzq7Y0fS/+6tam9E34m6k72ALmgkOeJdik="
            }
          },
          "QdtDn/KJ9zZ7NBe3ujpcpWV4K0ZyWJQNBHWmQDyvUkw=": {
            "valueMac": {
              "type": "Buffer",
              "data": "O+GI2UWNF1WoJcf5ZUide7aQ8JgMfb3rT2GWbAzcCX0="
            }
          }
        }
      }
    },
    "senderKeys": {
      "status@broadcast::6285773400911::0": [
        {
          "senderKeyId": 951649663,
          "senderChainKey": {
            "iteration": 16,
            "seed": "2oDk7CZdYQGJd7/otwoPRk2NQqaPNALYWb+efr9Coyw="
          },
          "senderSigningKey": {
            "public": "BSB1gsBwDldXV7/6haYXtRwFkpo2wheQvREb7DAM56Ec"
          },
          "senderMessageKeys": [
            {},
            {},
            {}
          ]
        }
      ],
      "status@broadcast::6288740030517::0": [
        {
          "senderKeyId": 917331415,
          "senderChainKey": {
            "iteration": 2,
            "seed": "JzaIYvkBlQv9uyhjcRWirMjMrkag7TIAKjihUk8YtU0="
          },
          "senderSigningKey": {
            "public": "Bc8n0pyyJ1R6ETATMiFsdnhtGtUS9TAQPfkQ6zqI484Q"
          }
        }
      ],
      "status@broadcast::62881037052224::0": [
        {
          "senderKeyId": 432908033,
          "senderChainKey": {
            "iteration": 19,
            "seed": "pB1rkwXoo9P4I5NpUAMIw+bYAqDS0N4C796UVJvCmZo="
          },
          "senderSigningKey": {
            "public": "BRG6T8T0upw5hIlVLmrISsmlDMx52p6N9CdY3Q/vQls/"
          },
          "senderMessageKeys": []
        },
        {
          "senderKeyId": 432908033,
          "senderChainKey": {
            "iteration": 21,
            "seed": "1eq4cLdJTqbbRDkcXEAyLwTmHAOG/sNBPP0NjJryoHA="
          },
          "senderSigningKey": {
            "public": "BRG6T8T0upw5hIlVLmrISsmlDMx52p6N9CdY3Q/vQls/"
          },
          "senderMessageKeys": []
        },
        {
          "senderKeyId": 432908033,
          "senderChainKey": {
            "iteration": 23,
            "seed": "hF528LOKO1KTdchGe/K2Lr5aBaSHFMiP2bFMoeiTZ/w="
          },
          "senderSigningKey": {
            "public": "BRG6T8T0upw5hIlVLmrISsmlDMx52p6N9CdY3Q/vQls/"
          }
        },
        {
          "senderKeyId": 612170185,
          "senderChainKey": {
            "iteration": 1,
            "seed": "yIgdqogP95k071a195J2oJoa5ZOns4Fk1JkNeKjzbIQ="
          },
          "senderSigningKey": {
            "public": "BTv4KtDpEVoZqPSbhjQxQdShcyZh/6X4vMhXGrAG9gVS"
          }
        }
      ],
      "status@broadcast::6285821080627::0": [
        {
          "senderKeyId": 1322169548,
          "senderChainKey": {
            "iteration": 65,
            "seed": "nRCfmMCG0maxnDbv0DU6zTfPw7OMtyqXpXxecDDtW/o="
          },
          "senderSigningKey": {
            "public": "BUJnNieh2oagviE4pcgQSTk+xlqC8K1lW6sEQhyck0Q2"
          },
          "senderMessageKeys": [
            {},
            {},
            {},
            {},
            {},
            {},
            {},
            {}
          ]
        }
      ],
      "status@broadcast::6285353429957::0": [
        {
          "senderKeyId": 104745065,
          "senderChainKey": {
            "iteration": 8,
            "seed": "pOmLYo6ozgT7GrDpYmj0UhOuhjhMSNB3/qRA2+NYn0U="
          },
          "senderSigningKey": {
            "public": "BToHMo+AOTdcVQPjW5Zm7G+PMeIxML1WEHjeBw83SNII"
          },
          "senderMessageKeys": [
            {},
            {},
            {},
            {}
          ]
        },
        {
          "senderKeyId": 104745065,
          "senderChainKey": {
            "iteration": 4,
            "seed": "Za3k8i4wqvhKOjSNmNeuH65SXn/BFhFch9r2UYwe/VY="
          },
          "senderSigningKey": {
            "public": "BToHMo+AOTdcVQPjW5Zm7G+PMeIxML1WEHjeBw83SNII"
          }
        },
        {
          "senderKeyId": 104745065,
          "senderChainKey": {
            "iteration": 6,
            "seed": "3lXe5a8DcExMBcsFOA7BywdvmObo7pdN64Ijzwa+1Wc="
          },
          "senderSigningKey": {
            "public": "BToHMo+AOTdcVQPjW5Zm7G+PMeIxML1WEHjeBw83SNII"
          }
        }
      ],
      "status@broadcast::6287738331591::0": [
        {
          "senderKeyId": 6502239,
          "senderChainKey": {
            "iteration": 1,
            "seed": "+OSEyo4SkP6q8x50C/5WG3MbLzNM+b/K0AaneuNq4J0="
          },
          "senderSigningKey": {
            "public": "BYKAqL34EPyA2kjViMGI4d60n6YlQ30UEc6C0ztadYgS"
          }
        }
      ],
      "status@broadcast::6283834558105::0": [
        {
          "senderKeyId": 701018596,
          "senderChainKey": {
            "iteration": 4,
            "seed": "x/3i6qjNTXJ44bzzGs70hiB1gPODx4i/G/8vl/nhizY="
          },
          "senderSigningKey": {
            "public": "BZcQjYeFLVrft9BCbB0W1z6qUScTYSlT8wqVXmB+Cd5P"
          }
        }
      ],
      "120363023561317609@g.us::6285878075754::0": [
        {
          "senderKeyId": 1908280950,
          "senderChainKey": {
            "iteration": 1,
            "seed": "TGR084fHLJ6NdUCtzbTxc+iOJWF0zJ7PnBu0NdC1tww="
          },
          "senderSigningKey": {
            "public": "BewrOsCGAAf6kyhKfTb+eOPhA9Wol/Gr8hTH5Oa50Etc"
          }
        }
      ],
      "120363043315203938@g.us::6285878075754::0": [
        {
          "senderKeyId": 656256090,
          "senderChainKey": {
            "iteration": 7,
            "seed": "aSFMN/CFnlwd0q29lSkVJaPJJQYjPJAEl+tKBpeu3SQ="
          },
          "senderSigningKey": {
            "public": "BVHQfg0ZF8cwbS7efuSLfOZcbH/qUwbsk+AQXfvqLb8H"
          }
        }
      ],
      "120363043315203938@g.us::62895605816958:29::0": [
        {
          "senderKeyId": 1962940053,
          "senderChainKey": {
            "iteration": 6,
            "seed": "VET9NAxop+ER+wWQYIFZcdEFjBSw1U9nTJ5mzLApqe8="
          },
          "senderSigningKey": {
            "public": "BbhzHKE3I8MFNGdRMy+rtjGNa+Hncj44GJnmK77Op10e",
            "private": "qA2GfxoYIaVKcfPQ/tof7T/tLVLE4PoN0LSBfYgJI3w="
          }
        }
      ],
      "120363043315203938@g.us::6289526217791::0": [
        {
          "senderKeyId": 398333472,
          "senderChainKey": {
            "iteration": 8,
            "seed": "YZ3RdwX8Bfq9qWNU122ft3E3lbCGlNd0QphcLJ6XVhI="
          },
          "senderSigningKey": {
            "public": "BehQAsC4R2NyabS1KnPWqRRE+YZjfE4xPfNE9ineabwy"
          },
          "senderMessageKeys": [
            {
              "iteration": 3,
              "seed": "O4JfTq7qphLoQ+HK+nIXzUsC62tPg8ZJ3Mfwjxa49CI="
            }
          ]
        }
      ],
      "status@broadcast::6289693024351::0": [
        {
          "senderKeyId": 255429042,
          "senderChainKey": {
            "iteration": 2,
            "seed": "b6IjpSBEwz/Plsb6yKPvU0TJYosWCc3PCEHgmBmMeuA="
          },
          "senderSigningKey": {
            "public": "Be38RWov63IB1QVjE5dqUhZoDc39ws4djyAuvO0d8mk6"
          },
          "senderMessageKeys": [
            {
              "iteration": 0,
              "seed": "xQsveIJ7tG6hUOfzl2faSraUATIhehBJQlMYk/Dw21Q="
            }
          ]
        }
      ]
    },
    "senderKeyMemory": {
      "120363043315203938@g.us": {
        "6285878075754@s.whatsapp.net": true,
        "6289526217791@s.whatsapp.net": true,
        "62895605816958@s.whatsapp.net": true,
        "62895605816958:28@s.whatsapp.net": true
      }
    }
  }
}